Workbook

Sheet Summary_Store
A1: No. | B1: Category | C1: Qty | D1: Notes | E1: HCM | F1: South stores (other than HCM) | G1: HN | H1: North stores (other than HN)
A2: 1 | B2: Number of active stores | C2: =COUNTIFS(#REF!,"Open",#REF!,"Store") + COUNTIFS(#REF!,"Open",#REF!,"Multi PC") + COUNTIFS(#REF!,"Open",#REF!,"Mono") + COUNTIFS(#REF!,"Open",#REF!,"SIS") -> #REF! | E2: =COUNTIFS(#REF!,"Open",#REF!,"Store",#REF!,"Ho Chi Minh City") + COUNTIFS(#REF!,"Open",#REF!,"Mono",#REF!,"Ho Chi Minh City") + COUNTIFS(#REF!,"Open",#REF!,"SIS",#REF!,"Ho Chi Minh City") -> #REF! | F2: =(COUNTIFS(#REF!,"Open",#REF!,"Store",#REF!,"South") + COUNTIFS(#REF!,"Open",#REF!,"Mono",#REF!,"South") + COUNTIFS(#REF!,"Open",#REF!,"SIS",#REF!,"South"))-E2 -> #REF! | G2: =COUNTIFS(#REF!,"Open",#REF!,"Store",#REF!,"Ha Noi") + COUNTIFS(#REF!,"Open",#REF!,"Mono",#REF!,"Ha Noi") + COUNTIFS(#REF!,"Open",#REF!,"SIS",#REF!,"Ha Noi") -> #REF! | H2: =(COUNTIFS(#REF!,"Open",#REF!,"Store",#REF!,"North") + COUNTIFS(#REF!,"Open",#REF!,"Mono",#REF!,"North") + COUNTIFS(#REF!,"Open",#REF!,"SIS",#REF!,"North"))-G2 -> #REF!
A3: =A2+1 -> 2 | B3: Number of active bazaar | C3: =COUNTIFS(#REF!,"Open",#REF!,"Bazaar") -> #REF!
A4: =A3+1 -> 3 | B4: Number of active events, private sales | C4: {=SUM(COUNTIFS(#REF!,"Open",#REF!,{"EVENT","PRIVATE SALE"}))} -> #REF!
A5: =A4+1 -> 4 | B5: Total (active) | C5: =SUM(C2:C4) -> #REF!
A6: =A5+1 -> 5 | B6: Existing stores that need to deploy FG-40F | C6: =COUNTIFS(#REF!,"Open",#REF!,"Need to deploy (FG-40F)") -> #REF!
A7: =A6+1 -> 6 | B7: Existing stores that need to deploy FG-60F | C7: =COUNTIFS(#REF!,"Need to deploy (FG-60F)") -> #REF!
A8: =A7+1 -> 7 | B8: Extra Details - Number of active Mono stores | C8: =COUNTIFS(#REF!,"Open",#REF!,"Store") + COUNTIFS(#REF!,"Open",#REF!,"Mono") -> #REF!
A9: =A8+1 -> 8 | B9: Extra Details - Number of active SIS stores | C9: =COUNTIFS(#REF!,"Open",#REF!,"Store") + COUNTIFS(#REF!,"Open",#REF!,"SIS") -> #REF!
A10: =A9+1 -> 9 | B10: Stores enabled O2O | C10: =COUNTIFS(#REF!,"Open",#REF!,"Yes") -> #REF!

Sheet Asset_Office
A1: No. | B1: Asset ID | C1: Status (formula) | D1: Assigned To (formula) | E1: Description (formula) | F1: Hostname | G1: AD User (formula) | H1: Location | I1: Asset Name (formula) | J1: Asset Type (formula) | K1: Brand | L1: Model | M1: S/N | N1: RAM (GB) | O1: Hard Disk (GB) | P1: Hard Disk Type | Q1: CPU | R1: Purchase Date | S1: Vendor/Supplier | T1: Note | V1: Assignment History | W1: USB TOKEN | X1: Old Hostname | Y1: AD unjoin, change hostname | Z1: PASTE ASSET ID | AA1: Status BIGFIX | AB1: STATUS Crowdstrike | AC1: STATUS JOIN DOMAIN
A2: 1 | B2: 22VN00000001 | C2: In Use | D2: =VLOOKUP(B2,VN_Emails!B:H,4,0) -> Tiet Nha Phung | E2: =VLOOKUP(B2,VN_Emails!B:H,7,0) -> Brand Manager (Converse) | F2: AMMAVNAMC000001 | G2: =SUBSTITUTE(VLOOKUP(B2,VN_Emails!B:H,2,0),"@mapactive.vn","") -> phung.tietnha | H2: Office | I2: =J2&" "&K2&" "&L2 -> Laptop HP Latitude 7420 | J2: Laptop | K2: HP | L2: Latitude 7420 | M2: DVV62J3 | N2: 16 | O2: 512 | P2: SSD | Q2: 1700 MHz 11th Gen Intel Core i7-1165G7 @ 2.80GHz | X2: MMA-LAP-0001 | Y2: DONE | Z2: DONE | AA2: DONE | AB2: DONE | AC2: Created it.active local account
A3: =A2+1 -> 2 | B3: 22VN00000002 | C3: In Use | D3: =VLOOKUP(B3,VN_Emails!B:H,4,0) -> Doan Thien Ho An | E3: =VLOOKUP(B3,VN_Emails!B:H,7,0) -> Digital Marketing Manager | F3: AMMAVNACC000002 | G3: =SUBSTITUTE(VLOOKUP(B3,VN_Emails!B:H,2,0),"@mapactive.vn","") -> Doan.An | H3: Office | I3: =J3&" "&K3&" "&L3 -> Laptop Dell Latitude 7420 | J3: Laptop | K3: Dell | L3: Latitude 7420 | M3: 124N1J3 | N3: 16 | O3: 512 | P3: SSD | Q3: 1700 MHz 11th Gen Intel Core i7-1165G7 @ 2.80GHz | V3: DANG BH LAPTOP KO LÊN NGUỒN | X3: MMA-LAP-0002 | Y3: Need to do both | Z3: DONE | AA3: DONE | AB3: DONE
A4: =A3+1 -> 3 | B4: 22VN00000003 | C4: Available | D4: =VLOOKUP(B4,VN_Emails!B:H,4,0) -> #N/A | E4: =VLOOKUP(B4,VN_Emails!B:H,7,0) -> #N/A | F4: AMMAVNACC000003 | G4: =SUBSTITUTE(VLOOKUP(B4,VN_Emails!B:H,2,0),"@mapactive.vn","") -> #N/A | H4: Office | I4: =J4&" "&K4&" "&L4 -> Laptop Dell Latitude 5420 | J4: Laptop | K4: Dell | L4: Latitude 5420 | M4: 1Z8DZH3 | N4: 16 | O4: 512 | P4: SSD | Q4: 1400 MHz 11th Gen Intel Core i5-1135G7 @ 2.40GHz | T4: UPDATE NEW SSD 500GB SAMSUNG | V4: đã bh ssd vs CMCSG samsung 500GB lưu kho IT Lấy ổ cứng SSD đã bảo hành của chị Mai (M.2 SSD - Model A60 - 512GB - S/N: 23027592-050170B) để thay vào laptop Dell Latitude 7420 của chị Uyên Máy cũ chị Maya đã thu hồi 22/01/2024 , Hiếu IT đang giữ | W4: use USB token | X4: MMA-LAP-0003 | Y4: DONE | Z4: DONE | AA4: DONE | AB4: DONE
A5: =A4+1 -> 4 | B5: 22VN00000004 | C5: In Use | D5: =VLOOKUP(B5,VN_Emails!B:H,4,0) -> Nguyen Thi Thuy Mong | E5: =VLOOKUP(B5,VN_Emails!B:H,7,0) -> Senior Brand Marketing Manager | F5: AMMAVNACC000004 | G5: =SUBSTITUTE(VLOOKUP(B5,VN_Emails!B:H,2,0),"@mapactive.vn","") -> mong.nguyenthithuy | H5: Office | I5: =J5&" "&K5&" "&L5 -> Laptop Dell Latitude 5430 | J5: Laptop | K5: Dell | L5: Latitude 5430 | M5: 42X2SQ3 | N5: 8 | O5: 512 | P5: SSD | Q5: 2500 MHz 12th Gen Intel Core i5-1235U | V5: Máy của Danh thỉnh thoảng không lên màn hình | X5: MMA-LAP-0004 | Y5: DONE | Z5: DONE | AA5: DONE | AB5: DONE
A6: =A5+1 -> 5 | B6: 22VN00000006 | C6: In Use | D6: =VLOOKUP(B6,VN_Emails!B:H,4,0) -> Le Hong Bao Chau | E6: old laptop Nguyen Hoang Anh Thy Accounting | F6: AMMAVNACC000006 | H6: Office | I6: =J6&" "&K6&" "&L6 -> Laptop Dell Latitude 3520 | J6: Laptop | K6: Dell | L6: Latitude 3520 | M6: 5R4JGL3 | N6: 8 | O6: 256 | P6: SSD | Q6: 1400 MHz 11th Gen Intel Core i5-1135G7 @ 2.40GHz | V6: old laptop Nguyen Hoang Anh Thy Accounting, IT thu hồi 21-02-2024 | X6: AMMAVNACC000006 | Y6: DONE | Z6: DONE | AA6: DONE | AB6: DONE
A7: =A6+1 -> 6 | B7: 22VN00000007 | C7: In Use | D7: =VLOOKUP(B7,VN_Emails!B:H,4,0) -> Van Huynh Tu Trinh | E7: =VLOOKUP(B7,VN_Emails!B:H,7,0) -> Receivable Accountant | F7: AMMAVNACCC000007 | G7: =SUBSTITUTE(VLOOKUP(B7,VN_Emails!B:H,2,0),"@mapactive.vn","") -> trinh.vanhuynhtu | H7: Office | I7: =J7&" "&K7&" "&L7 -> Laptop Dell Latitude 3420 | J7: Laptop | K7: Dell | L7: Latitude 3420 | M7: 65G48S3 | N7: 16 | O7: 512 | P7: SSD | Q7: 1400 MHz 11th Gen Intel Core i5-1135G7 @ 2.40GHz | X7: MMA-LAP-0007 | Y7: DONE | Z7: DONE | AA7: DONE | AB7: DONE
A8: =A7+1 -> 7 | B8: 22VN00000008 | C8: Available | D8: =VLOOKUP(B8,VN_Emails!B:H,4,0) -> #N/A | E8: =VLOOKUP(B8,VN_Emails!B:H,7,0) -> #N/A | F8: AMMAVNACC000008 | G8: =SUBSTITUTE(VLOOKUP(B8,VN_Emails!B:H,2,0),"@mapactive.vn","") -> #N/A | H8: Office | I8: =J8&" "&K8&" "&L8 -> Laptop Dell Latitude 3520 | J8: Laptop | K8: Dell | L8: Latitude 3520 | M8: 2P8VKG3 | N8: 8 | O8: 512 | P8: SSD | Q8: 1400 MHz 11th Gen Intel Core i3-1135G7 @ 2.40GHz | W8: use USB token | X8: MMA-LAP-0008 | Y8: DONE | Z8: DONE | AA8: DONE | AB8: DONE
A9: =A8+1 -> 8 | B9: 22VN00000009 | C9: In Use | D9: =VLOOKUP(B9,VN_Emails!B:H,4,0) -> Le Cam Linh | E9: =VLOOKUP(B9,VN_Emails!B:H,7,0) -> Shipping Supervisor | F9: AMMAVNLOC000009 | G9: =SUBSTITUTE(VLOOKUP(B9,VN_Emails!B:H,2,0),"@mapactive.vn","") -> linh.lecam | H9: Office | I9: =J9&" "&K9&" "&L9 -> Laptop Dell Latitude 5430 | J9: Laptop | K9: Dell | L9: Latitude 5430 | M9: 1583SQ3 | N9: 20 | O9: 512 | P9: SSD | Q9: 2500 MHz 12th Gen Intel Core i5-1235U | X9: MMA-LAP-0009 | Y9: DONE | AA9: DONE | AB9: DONE
A10: =A9+1 -> 9 | B10: 22VN00000010 | C10: In Use | D10: =VLOOKUP(B10,VN_Emails!B:H,4,0) -> Vo Ngoc Thanh Ngan | E10: =VLOOKUP(B10,VN_Emails!B:H,7,0) -> Intern | F10: AMMAVNROC000010 | G10: =SUBSTITUTE(VLOOKUP(B10,VN_Emails!B:H,2,0),"@mapactive.vn","") -> ngan.vongocthanh | H10: Office | I10: =J10&" "&K10&" "&L10 -> Laptop Dell Latitude 3520 | J10: Laptop | K10: Dell | L10: Latitude 3520 | M10: 4Q9VKG3 | N10: 8 | O10: 256 | P10: SSD | Q10: 2200 MHz 11th Gen Intel Core i3-1115G4 @ 3.00GHz | V10: Máy Mỹ TRang cũ | X10: MMA-LAP-0010 | Y10: DONE | Z10: DONE | AA10: DONE | AB10: DONE
A11: =A10+1 -> 10 | B11: 22VN00000011 | C11: In Use | D11: =VLOOKUP(B11,VN_Emails!B:H,4,0) -> Nguyen Bao Ngoc | E11: =VLOOKUP(B11,VN_Emails!B:H,7,0) -> Division Operation Manager | F11: AMMAVNMDC000011 | G11: =SUBSTITUTE(VLOOKUP(B11,VN_Emails!B:H,2,0),"@mapactive.vn","") -> Ngoc.nguyenbao | H11: Office | I11: =J11&" "&K11&" "&L11 -> Laptop Dell Latitude 5430 | J11: Laptop | K11: Dell | L11: Latitude 5430 | M11: F083SQ3 | N11: 8 | O11: 512 | P11: SSD | Q11: 2500 MHz 12th Gen Intel Core i5-1235U | V11: SỬ DỤNG MÁY 5430 CỦA LƯU GIANG CẨM VÂN(VICKY) ĐÃ THAY SSD BỊ HƯ TỪ CMC (LẦN 1) CHỜ CỨU DATA TỪ SÓNG NAM SAU ĐÓ BH SSD VS CMC(SAU TẾT) CMC ĐÃ GỬI LẠI SSD MỚI NGÀY 08/03/2024 | X11: MMA-LAP-0011 | Y11: DONE | Z11: DONE | AA11: DONE | AB11: DONE
A12: =A11+1 -> 11 | B12: 22VN00000012 | C12: Available | D12: =VLOOKUP(B12,VN_Emails!B:H,4,0) -> #N/A | E12: =VLOOKUP(B12,VN_Emails!B:H,7,0) -> #N/A | F12: AMMAVNHRC000012 | G12: =SUBSTITUTE(VLOOKUP(B12,VN_Emails!B:H,2,0),"@mapactive.vn","") -> #N/A | H12: Office | I12: =J12&" "&K12&" "&L12 -> Laptop Dell Latitude 3520 | J12: Laptop | K12: Dell | L12: Latitude 3520 | M12: BR9VKG3 | N12: 8 | O12: 256 | P12: SSD | Q12: 2200 MHz 11th Gen Intel Core i3-1115G4 @ 3.00GHz | T12: Máy lỗi loa user binh.ngotieu 16/05/24, Cấp tạm cho Lan Vy Cấp ZV16 26/08/2024 | X12: MMA-LAP-0012 | Y12: DONE | Z12: DONE | AA12: DONE | AB12: DONE
A13: =A12+1 -> 12 | B13: 22VN00000013 | C13: In Use | D13: =VLOOKUP(B13,VN_Emails!B:H,4,0) -> Tran Thi Yen Nhi | E13: =VLOOKUP(B13,VN_Emails!B:H,7,0) -> Payroll & Em. Servieces Executive | F13: AMMAVNHRC000013 | G13: =SUBSTITUTE(VLOOKUP(B13,VN_Emails!B:H,2,0),"@mapactive.vn","") -> nhi.tranthiyen | H13: Office | I13: =J13&" "&K13&" "&L13 -> Laptop HP Pavilion 15-eg0xxx | J13: Laptop | K13: HP | L13: Pavilion 15-eg0xxx | M13: 5CD1294NHX | N13: 8 | O13: 512 | P13: SSD | Q13: 2400 MHz 11th Gen Intel Core i5-1135G7 @ 2.40GHz | W13: use USB token | X13: MMA-LAP-0013 | Y13: DONE | Z13: DONE | AA13: DONE | AB13: DONE
A14: =A13+1 -> 13 | B14: 22VN00000014 | C14: In Use | D14: =VLOOKUP(B14,VN_Emails!B:H,4,0) -> Ni Ksormahhko | E14: =VLOOKUP(B14,VN_Emails!B:H,7,0) -> Procurement Executive | F14: AMMAVNPUC000014 | G14: =SUBSTITUTE(VLOOKUP(B14,VN_Emails!B:H,2,0),"@mapactive.vn","") -> ni.ksormahhko | H14: Office | I14: =J14&" "&K14&" "&L14 -> Laptop Dell Latitude 3520 | J14: Laptop | K14: Dell | L14: Latitude 3520 | M14: BKY5FX3 | N14: 8 | O14: 256 | P14: SSD | Q14: 11TH Gen Intel ® Core™ i5-1135G7 @2.40Ghz | X14: MMA-LAP-0014 | Y14: DONE | Z14: DONE | AA14: DONE | AB14: DONE
A15: =A14+1 -> 14 | B15: 22VN00000015 | C15: In Use | D15: =VLOOKUP(B15,VN_Emails!B:H,4,0) -> Huynh Tuan Nhan | E15: =VLOOKUP(B15,VN_Emails!B:H,7,0) -> SCM Manager | F15: AMMAVNLOC000015 | G15: =SUBSTITUTE(VLOOKUP(B15,VN_Emails!B:H,2,0),"@mapactive.vn","") -> nhan.huynhtuan | H15: Office | I15: =J15&" "&K15&" "&L15 -> Laptop Dell Latitude 5430 | J15: Laptop | K15: Dell | L15: Latitude 5430 | M15: 13D4SQ3 | N15: 16 | O15: 512 | P15: SSD | Q15: 2500 MHz 12th Gen Intel Core i5-1235U | X15: MMA-LAP-0015 | Y15: DONE | Z15: DONE | AA15: DONE | AB15: DONE
A16: =A15+1 -> 15 | B16: 22VN00000016 | C16: Available | D16: =VLOOKUP(B16,VN_Emails!B:H,4,0) -> #N/A | E16: =VLOOKUP(B16,VN_Emails!B:H,7,0) -> #N/A | F16: AMMAVNLOC000016 | G16: =SUBSTITUTE(VLOOKUP(B16,VN_Emails!B:H,2,0),"@mapactive.vn","") -> #N/A | H16: Office | I16: =J16&" "&K16&" "&L16 -> Laptop Dell Latitude 3520 | J16: Laptop | K16: Dell | L16: Latitude 3520 | M16: 99C2LG3 | N16: 12 | O16: 512 | P16: SSD | Q16: 2200 MHz 11th Gen Intel Core i3-1115G4 @ 3.00GHz | T16: Nâng 4gb Ram và 256GB SSD | X16: MMA-LAP-0016 | Y16: DONE | Z16: DONE | AA16: DONE | AB16: DONE
A17: =A16+1 -> 16 | B17: 22VN00000017 | C17: Available | D17: =VLOOKUP(B17,VN_Emails!B:H,4,0) -> #N/A | E17: =VLOOKUP(B17,VN_Emails!B:H,7,0) -> #N/A | F17: AMMAVNWHC000017 | G17: =SUBSTITUTE(VLOOKUP(B17,VN_Emails!B:H,2,0),"@mapactive.vn","") -> #N/A | H17: Office | I17: =J17&" "&K17&" "&L17 -> Laptop Dell Latitude 3520 | J17: Laptop | K17: Dell | L17: Latitude 3520 | M17: JP8VKG3 | N17: 16 | O17: 256 | P17: SSD | Q17: 2200 MHz 11th Gen Intel Core i3-1115G4 @ 3.00GHz | X17: MMA-LAP-0017 | Y17: DONE | Z17: DONE | AA17: DONE | AB17: DONE
A18: =A17+1 -> 17 | B18: 22VN00000018 | C18: In Use | D18: =VLOOKUP(B18,VN_Emails!B:H,4,0) -> Dang Thanh Nam | E18: =VLOOKUP(B18,VN_Emails!B:H,7,0) -> Warehouse and Distribution Supervisor | F18: AMMAVNWHC000018 | G18: =SUBSTITUTE(VLOOKUP(B18,VN_Emails!B:H,2,0),"@mapactive.vn","") -> nam.dangthanh | H18: Office | I18: =J18&" "&K18&" "&L18 -> Laptop Dell Latitude 3520 | J18: Laptop | K18: Dell | L18: Latitude 3520 | M18: JR9VKG3 | N18: 8 | O18: 256 | P18: SSD | Q18: 2200 MHz 11th Gen Intel Core i3-1115G4 @ 3.00GHz | X18: MMA-LAP-0018 | Y18: DONE | Z18: DONE | AA18: DONE | AB18: DONE
A19: =A18+1 -> 18 | B19: 22VN00000019 | C19: Available | E19: =VLOOKUP(B19,VN_Emails!B:H,7,0) -> #N/A | F19: AMMAVNLOC000019 | G19: =SUBSTITUTE(VLOOKUP(B19,VN_Emails!B:H,2,0),"@mapactive.vn","") -> #N/A | H19: Office | I19: =J19&" "&K19&" "&L19 -> Laptop Dell Latitude 3520 | J19: Laptop | K19: Dell | L19: Latitude 3520 | M19: FQ8VKG3 | N19: 8 | O19: 256 | P19: SSD | Q19: 2200 MHz 11th Gen Intel Core i3-1115G4 @ 3.00GHz | X19: MMA-LAP-0019 | Y19: DONE | Z19: DONE | AA19: DONE | AB19: DONE
A20: =A19+1 -> 19 | B20: 22VN00000020 | C20: In Use | D20: Quan Thanh Them | E20: =VLOOKUP(B20,VN_Emails!B:H,7,0) -> COE Manager | F20: AMMAVNCEC000020 | G20: =SUBSTITUTE(VLOOKUP(B20,VN_Emails!B:H,2,0),"@mapactive.vn","") -> them.quanthanh | H20: Office | I20: =J20&" "&K20&" "&L20 -> Laptop Dell Latitude 5430 | J20: Laptop | K20: Dell | L20: Latitude 5430 | M20: 5BD4SQ3 | N20: 16 | O20: 512 | P20: SSD | Q20: 2500 MHz 12th Gen Intel Core i5-1235U | X20: MMA-LAP-0020 | Y20: DONE | Z20: DONE | AA20: DONE | AB20: DONE
A21: =A20+1 -> 20 | B21: 22VN00000021 | C21: In Use | D21: =VLOOKUP(B21,VN_Emails!B:H,4,0) -> Nguyen Ngoc Xuan Duyen | E21: =VLOOKUP(B21,VN_Emails!B:H,7,0) -> COE Officer | F21: AMMAVNCEC000021 | G21: =SUBSTITUTE(VLOOKUP(B21,VN_Emails!B:H,2,0),"@mapactive.vn","") -> duyen.nguyenngocxuan | H21: Office | I21: =J21&" "&K21&" "&L21 -> Laptop Dell Latitude 3520 | J21: Laptop | K21: Dell | L21: Latitude 3520 | M21: BTN0BG3 | N21: 8 | O21: 256 | P21: SSD | Q21: 2200 MHz 11th Gen Intel Core i3-1115G4 @ 3.00GHz | X21: MMA-LAP-0021 | Y21: DONE | Z21: DONE | AA21: DONE | AB21: DONE
A22: =A21+1 -> 21 | B22: 22VN00000022 | C22: In Use | D22: =VLOOKUP(B22,VN_Emails!B:H,4,0) -> Nguyen Quyet Thang | E22: =VLOOKUP(B22,VN_Emails!B:H,7,0) -> COE Officer | F22: AMMAVNCEC000022 | G22: thang.nguyenquyet | H22: Office | I22: =J22&" "&K22&" "&L22 -> Laptop Dell Latitude 3520 | J22: Laptop | K22: Dell | L22: Latitude 3520 | M22: DP8VKG3 | N22: 8 | O22: 256 | P22: SSD | Q22: 2200 MHz 11th Gen Intel Core i3-1115G4 @ 3.00GHz | V22: LE MINH KHANG OLD LAPTOP (COE Officer) resigned 29-01-2024 - 25/03/2024 handover for Tạ Quỳnh Trang -16/07/2024 handover for Trần Hồ Duy Tân | X22: MMA-LAP-0022 | Y22: DONE | Z22: DONE | AA22: DONE | AB22: DONE
A23: =A22+1 -> 22 | B23: 22VN00000023 | C23: In Use | D23: =VLOOKUP(B23,VN_Emails!B:H,4,0) -> Nguyen Bao Du | E23: IT BACKUP | F23: AMMAVNCEC000023 | H23: Office | I23: =J23&" "&K23&" "&L23 -> Laptop Dell Latitude 3520 | J23: Laptop | K23: Dell | L23: Latitude 3520 | M23: 6S4JGL3 | N23: 8 | O23: 256 | P23: SSD | Q23: 1400 MHz 11th Gen Intel Core i5-1135G7 @ 2.40GHz | V23: - Tran Dang Anh Khoa (COE Officer) resigned - Cấp tạm cho DƯƠNG QUANG MINH TUẤN THAY cho HỒ HẢI ĐĂNG AM IT ĐÃ THU HỒI 30-01-24 | W23: DISABLE | X23: MMA-LAP-0023 | Y23: DONE | Z23: DONE | AA23: DONE | AB23: DONE | AC23: DONE
A24: =A23+1 -> 23 | B24: 22VN00000024 | C24: Available | D24: =VLOOKUP(B24,VN_Emails!B:H,4,0) -> #N/A | E24: =VLOOKUP(B24,VN_Emails!B:H,7,0) -> #N/A | F24: AMMAVNICC000024 | G24: =SUBSTITUTE(VLOOKUP(B24,VN_Emails!B:H,2,0),"@mapactive.vn","") -> #N/A | H24: Office | I24: =J24&" "&K24&" "&L24 -> Laptop Dell Latitude 3520 | J24: Laptop | K24: Dell | L24: Latitude 3520 | M24: 4R9VKG3 | N24: 8 | O24: 256 | P24: SSD | Q24: 2200 MHz 11th Gen Intel Core i3-1115G4 @ 3.00GHz | X24: MMA-LAP-0024 | Y24: DONE | Z24: DONE | AA24: DONE | AB24: DONE
A25: =A24+1 -> 24 | B25: 22VN00000025 | C25: In Use | D25: =VLOOKUP(B25,VN_Emails!B:H,4,0) -> Luong Huu Quan | E25: =VLOOKUP(B25,VN_Emails!B:H,7,0) -> IT Infrastructure & Operations Supervisor | F25: AMMAVNITC000025 | G25: =SUBSTITUTE(VLOOKUP(B25,VN_Emails!B:H,2,0),"@mapactive.vn","") -> quan.luonghuu | H25: Office | I25: =J25&" "&K25&" "&L25 -> Laptop Dell Latitude 5430 | J25: Laptop | K25: Dell | L25: Latitude 5430 | M25: FGF3SQ3 | N25: 16 | O25: 512 | P25: SSD | Q25: 2500 MHz 12th Gen Intel Core i5-1235U | X25: MMA-LAP-0025 | Y25: DONE | Z25: DONE | AA25: DONE | AB25: DONE
A26: =A25+1 -> 25 | B26: 22VN00000026 | C26: Available | D26: IT BACKUP | E26: IT BACKUP | F26: AMMAVNITC000026 | H26: Office | I26: =J26&" "&K26&" "&L26 -> Laptop HP ProBook 440 G4 | J26: Laptop | K26: HP | L26: ProBook 440 G4 | M26: 5CD73626Y5 | N26: 16 | O26: 256 | P26: SSD | Q26: 2700 MHz Core i5-7200U | T26: anh.nguyenphamduy resigned 20/05/2024 | V26: -Dat.tranquoc (IT Officer) resigned 11/3/2024 | X26: MMA-LAP-0026 | Y26: DONE | Z26: DONE | AA26: DONE | AB26: DONE | AC26: DONE
A27: =A26+1 -> 26 | B27: 22VN00000027 | C27: In Use | D27: =VLOOKUP(B27,VN_Emails!B:H,4,0) -> Huynh My Danh | E27: =VLOOKUP(B27,VN_Emails!B:H,7,0) -> FP&A Supervisor | F27: AMMAVNMRC000027 | G27: =SUBSTITUTE(VLOOKUP(B27,VN_Emails!B:H,2,0),"@mapactive.vn","") -> danh.huynhmy | H27: Office | I27: =J27&" "&K27&" "&L27 -> Laptop Dell Latitude 5420 | J27: Laptop | K27: Dell | L27: Latitude 5420 | M27: HRQCZH3 | N27: 8 | O27: 512 | P27: SSD | Q27: 1400 MHz 11th Gen Intel Core i5-1135G7 @ 2.40GHz | X27: MMA-LAP-0027 | Y27: DONE | Z27: DONE | AA27: DONE | AB27: DONE
A28: =A27+1 -> 27 | B28: 22VN00000028 | C28: In Use | D28: =VLOOKUP(B28,VN_Emails!B:H,4,0) -> Nghiem Thi Hong Van | E28: =VLOOKUP(B28,VN_Emails!B:H,7,0) -> Senior Merchandise | F28: AMMAVNMDCC000028 | G28: =SUBSTITUTE(VLOOKUP(B28,VN_Emails!B:H,2,0),"@mapactive.vn","") -> van.nghiemthihong | H28: Office | I28: =J28&" "&K28&" "&L28 -> Laptop Dell Latitude 3520 | J28: Laptop | K28: Dell | L28: Latitude 3520 | M28: GN8VKG3 | N28: 12 | O28: 256 | P28: SSD | Q28: 2200 MHz 11th Gen Intel Core i3-1115G4 @ 3.00GHz | T28: BÀN GIAO CHO Nghiêm Thị Hồng Vân – Senior Merchandise – Brand Department – On board 15/10/2023 (nâng 4gb Ram) | V28: MÁY CŨ LÊ TRẦN THIÊN MINH | X28: MMA-LAP-0028 | Y28: DONE | Z28: DONE | AA28: DONE | AB28: DONE
A29: =A28+1 -> 28 | B29: 22VN00000029 | C29: Available | D29: =VLOOKUP(B29,VN_Emails!B:H,4,0) -> #N/A | E29: =VLOOKUP(B29,VN_Emails!B:H,7,0) -> #N/A | F29: AMMAVNITC000029 | G29: =SUBSTITUTE(VLOOKUP(B29,VN_Emails!B:H,2,0),"@mapactive.vn","") -> #N/A | H29: Office | I29: =J29&" "&K29&" "&L29 -> Laptop Dell Latitude 3520 | J29: Laptop | K29: Dell | L29: Latitude 3520 | M29: 1P8VKG3 | N29: 8 | O29: 256 | P29: SSD | Q29: 2200 MHz 11th Gen Intel Core i3-1115G4 @ 3.00GHz | T29: Máy cũ Minh (sracecrow) | V29: Pham Thi Bao Tram (MKT) handover Feb-29-2024 Old hostname: AMMAVNMRC000029 | X29: MMA-LAP-0029 | Y29: DONE | Z29: DONE | AA29: DONE | AB29: DONE
A30: =A29+1 -> 29 | B30: 22VN00000030 | C30: Available | E30: Huynh Thi Bich Ngan resigned NGuyenThao My resigned 13/11/2024 | F30: AMMAVNMRC000030 | G30: =SUBSTITUTE(VLOOKUP(B30,VN_Emails!B:H,2,0),"@mapactive.vn","") -> #N/A | H30: Office | I30: =J30&" "&K30&" "&L30 -> Laptop Lenovo Thinkpad X280 | J30: Laptop | K30: Lenovo | L30: Thinkpad X280 | M30: PC133K78 | N30: 8 | O30: 256 | P30: SSD | Q30: 1800 MHz Core i5-8250U | T30: - Replaced keyboard on 20-Aug-2023 cấp cho :Nguyen Thao My 27/11/2023 (replace Phan Thi Thuy Tien) | V30: - Phan Thị Thủy Tiên đã thôi việc ngày 06/10/23 - Huỳnh Thị Bích Ngân – thôi việc ngày 13/10/2023 | X30: MMA-LAP-0030 | Y30: DONE | Z30: DONE | AA30: DONE | AB30: DONE | AC30: DONE
A31: =A30+1 -> 30 | B31: 22VN00000031 | C31: Available | D31: =VLOOKUP(B31,VN_Emails!B:H,4,0) -> #N/A | E31: =VLOOKUP(B31,VN_Emails!B:H,7,0) -> #N/A | F31: AMMAVNMDC000031 | G31: =SUBSTITUTE(VLOOKUP(B31,VN_Emails!B:H,2,0),"@mapactive.vn","") -> #N/A | H31: Office | I31: =J31&" "&K31&" "&L31 -> Laptop Dell Latitude 5420 | J31: Laptop | K31: Dell | L31: Latitude 5420 | M31: 4DBCZH3 | N31: 8 | O31: 512 | P31: SSD\ | Q31: 1400 MHz 11th Gen Intel Core i5-1135G7 @ 2.40GHz | X31: MMA-LAP-0031 | Y31: DONE | Z31: DONE | AA31: DONE | AB31: DONE
A32: =A31+1 -> 31 | B32: 22VN00000032 | C32: In Use | D32: =VLOOKUP(B32,VN_Emails!B:H,4,0) -> Vu Xuan Uyen | E32: =VLOOKUP(B32,VN_Emails!B:H,7,0) -> Marketing officer | F32: AMMAVNLEC000032 | G32: =SUBSTITUTE(VLOOKUP(B32,VN_Emails!B:H,2,0),"@mapactive.vn","") -> uyen.vuxuan | H32: Office | I32: =J32&" "&K32&" "&L32 -> Laptop Dell Latitude 3420 | J32: Laptop | K32: Dell | L32: Latitude 3420 | M32: 6GV7R93 | N32: 8 | O32: 640 | P32: HDD (512 GB) SSD (128 GB) | Q32: 1400 MHz 11th Gen Intel Core i5-1135G7 @ 2.40GHz | T32: Quỳnh MD Bàn giao trả máy ngày 24/08/2023 > Chuyển sang cho Le Thi Kim Hồng (Legal) sử dụng ngày 11/09/2023 | W32: use USB token | X32: MMA-LAP-0032 | Y32: DONE | Z32: DONE | AA32: DONE | AB32: DONE
A33: =A32+1 -> 32 | B33: 22VN00000033 | C33: Available | D33: =VLOOKUP(B33,VN_Emails!B:H,4,0) -> #N/A | E33: =VLOOKUP(B33,VN_Emails!B:H,7,0) -> #N/A | F33: AMMAVNMDC000033 | G33: =SUBSTITUTE(VLOOKUP(B33,VN_Emails!B:H,2,0),"@mapactive.vn","") -> #N/A | H33: Office | I33: =J33&" "&K33&" "&L33 -> Laptop Dell Latitude 3520 | J33: Laptop | K33: Dell | L33: Latitude 3520 | M33: 9P8VKG3 | N33: 8 | O33: 256 | P33: SSD | Q33: 2200 MHz 11th Gen Intel Core i3-1115G4 @ 3.00GHz | X33: MMA-LAP-0033 | Y33: DONE | Z33: DONE | AA33: DONE | AB33: DONE
A34: =A33+1 -> 33 | B34: 22VN00000034 | C34: In Use | D34: =VLOOKUP(B34,VN_Emails!B:H,4,0) -> Tran A giang | E34: =VLOOKUP(B34,VN_Emails!B:H,7,0) -> Intern | F34: AMMAVNMDC000034 | G34: =SUBSTITUTE(VLOOKUP(B34,VN_Emails!B:H,2,0),"@mapactive.vn","") -> giang.trana | H34: Office | I34: =J34&" "&K34&" "&L34 -> Laptop Dell Latitude 3520 | J34: Laptop | K34: Dell | L34: Latitude 3520 | M34: DGBJGL3 | N34: 8 | O34: 256 | P34: SSD | Q34: 1400 MHz 11th Gen Intel Core i5-1135G7 @ 2.40GHz | X34: MMA-LAP-0034 | Y34: DONE | Z34: DONE | AA34: DONE | AB34: DONE
A35: =A34+1 -> 34 | B35: 22VN00000035 | C35: In Use | D35: =VLOOKUP(B35,VN_Emails!B:H,4,0) -> Dang Thi Thanh Tam | E35: =VLOOKUP(B35,VN_Emails!B:H,7,0) -> Brand Manager (NB, Crocs) | F35: AMMAVNMDC000035 | G35: =SUBSTITUTE(VLOOKUP(B35,VN_Emails!B:H,2,0),"@mapactive.vn","") -> tam.dangthithanh | H35: Office | I35: =J35&" "&K35&" "&L35 -> Laptop Dell Latitude 5420 | J35: Laptop | K35: Dell | L35: Latitude 5420 | M35: 4CBCZH3 | N35: 12 | O35: 512 | P35: SSD | Q35: 1400 MHz 11th Gen Intel Core i5-1135G7 @ 2.40GHz | X35: MMA-LAP-0035 | Y35: DONE | Z35: DONE | AA35: DONE | AB35: DONE
A36: =A35+1 -> 35 | B36: 22VN00000036 | C36: Reserved | D36: KN10 bán cho Maison | E36: Pham My Tu old laptop | F36: AMMAVNMDC000036 | H36: Office | I36: =J36&" "&K36&" "&L36 -> Laptop Lenovo Ideapad 5-15ITL05(82FG00M5VN) | J36: Laptop | K36: Lenovo | L36: Ideapad 5-15ITL05(82FG00M5VN) | M36: PF2Q30RQ | N36: 8 | O36: 512 | P36: SSD | Q36: 2400 MHz 11th Gen Intel Core i5-1135G7 @ 2.40GHz | T36: - Old laptop of Pham My Tu - Cần cài lại Windows | V36: - Old laptop of Pham My Tu | X36: MMA-LAP-0036 | Y36: DONE | Z36: DONE | AA36: DONE | AB36: DONE
A37: =A36+1 -> 36 | B37: 22VN00000037 | C37: In Use | D37: =VLOOKUP(B37,VN_Emails!B:H,4,0) -> Nguyen Phuoc Thanh | E37: =VLOOKUP(B37,VN_Emails!B:H,7,0) -> Merchandiser | F37: AMMAVNMDC000037 | G37: =SUBSTITUTE(VLOOKUP(B37,VN_Emails!B:H,2,0),"@mapactive.vn","") -> thanh.nguyenphuoc | H37: Office | I37: =J37&" "&K37&" "&L37 -> Laptop Dell Latitude 3520 | J37: Laptop | K37: Dell | L37: Latitude 3520 | M37: 6Q7JGL3 | N37: 12 | O37: 512 | P37: SSD | Q37: 1400 MHz 11th Gen Intel Core i5-1135G7 @ 2.40GHz | X37: MMA-LAP-0037 | Y37: DONE | Z37: DONE | AA37: DONE | AB37: DONE
A38: =A37+1 -> 37 | B38: 22VN00000038 | C38: In Use | D38: =VLOOKUP(B38,VN_Emails!B:H,4,0) -> Ngo Thi Bich Tram | E38: Ms. Jolie resigned (keep for replacement) | F38: AMMAVNMDC000038 | G38: =SUBSTITUTE(VLOOKUP(B38,VN_Emails!B:H,2,0),"@mapactive.vn","") -> tram.ngothibich | H38: Office | I38: =J38&" "&K38&" "&L38 -> Laptop Dell Latitude 5430 | J38: Laptop | K38: Dell | L38: Latitude 5430 | M38: 4TS3SQ3 | N38: 16 | O38: 512 | P38: SSD | Q38: 2500 MHz 12th Gen Intel Core i5-1235U | V38: Máy của TRƯƠNG HỒNG HƯƠNG BÀN GIAO (HIếu IT giữ) | X38: MMA-LAP-0038 | Y38: DONE | Z38: DONE | AA38: DONE | AB38: DONE
A39: ost | B39: 22VN00000039 | C39: In Use | D39: =VLOOKUP(B39,VN_Emails!B:H,4,0) -> Le Ngoc Bich Tram | E39: =VLOOKUP(B39,VN_Emails!B:H,7,0) -> Marketing Supervisor (Foot Locker) | F39: AMMAVNIT000039 | G39: =SUBSTITUTE(VLOOKUP(B39,VN_Emails!B:H,2,0),"@mapactive.vn","") -> tram.lengocbich | H39: Office | I39: =J39&" "&K39&" "&L39 -> Laptop Dell Latitude 3520 | J39: Laptop | K39: Dell | L39: Latitude 3520 | M39: HGBJGL3 | N39: 20 | O39: 256+512 | P39: SSD | Q39: 1400 MHz 11th Gen Intel Core i5-1135G7 @ 2.40GHz | V39: linh.thainhat resigned 24/04/2024 | X39: MMA-LAP-0039 | Y39: DONE | Z39: DONE | AA39: DONE | AB39: DONE
A40: =#REF!+1 -> #REF! | B40: 22VN00000041 | C40: In Use | D40: =VLOOKUP(B40,VN_Emails!B:H,4,0) -> Nguyen Thi Tuyet Nhung | E40: Nguyen Thi Quynh Giang resigned | F40: AMMAVNBPC000041 | G40: minh.lengocbao | H40: Office | I40: =J40&" "&K40&" "&L40 -> Laptop Dell Latitude 5430 | J40: Laptop | K40: Dell | L40: Latitude 5430 | M40: GB23SQ3 | N40: 16 | O40: 512 | P40: SSD | Q40: 2500 MHz 12th Gen Intel Core i5-1235U | T40: User giang.nguyenthiquynh bàn giao ngày 18/08/2023 | V40: IT nhận máy bh ssd lỗi ngày 06/02/24(cmc)> BH SAU TẾT đã bh xong bàn giao user ngày 29/02/24 | W40: DISABLE | X40: MMA-LAP-0041 | Y40: DONE | Z40: DONE | AA40: DONE | AB40: DONE | AC40: DONE
A41: =A40+1 -> #REF! | B41: 22VN00000042 | C41: In Use | D41: =VLOOKUP(B41,VN_Emails!B:H,4,0) -> Tran Duy Dien | E41: =VLOOKUP(B41,VN_Emails!B:H,7,0) -> Inventory Control | F41: AMMAVNICC000042 | G41: =SUBSTITUTE(VLOOKUP(B41,VN_Emails!B:H,2,0),"@mapactive.vn","") -> dien.tranduy | H41: Office | I41: =J41&" "&K41&" "&L41 -> Laptop Dell Latitude 3520 | J41: Laptop | K41: Dell | L41: Latitude 3520 | M41: J94JGL3 | N41: 8 | O41: 256 | P41: SSD | Q41: 1400 MHz 11th Gen Intel Core i5-1135G7 @ 2.40GHz | X41: MMA-LAP-0042 | Y41: DONE | Z41: DONE | AA41: DONE | AB41: DONE
A42: =A41+1 -> #REF! | B42: 22VN00000043 | C42: In Use | D42: Nguyen Thi Minh Thu | E42: Huong Planning resigned (keep for replacement) | F42: AMMAVNITC000043 | H42: Office | I42: =J42&" "&K42&" "&L42 -> Laptop Dell Latitude 3520 | J42: Laptop | K42: Dell | L42: Latitude 3520 | M42: 8F6JGL3 | N42: 8 | O42: 256 | P42: SSD | Q42: 1400 MHz 11th Gen Intel Core i5-1135G7 @ 2.40GHz | T42: Hiếu IT giữ | V42: .TRẦN QUỐC THIÊN HƯƠNG (May) left on 26 Sep 2023 .Anh Hiếu đang giữ | X42: MMA-LAP-0043 | Y42: DONE | Z42: DONE | AA42: DONE | AB42: DONE
A43: =A42+1 -> #REF! | B43: 22VN00000044 | C43: In Use | D43: =VLOOKUP(B43,VN_Emails!B:H,4,0) -> Tran Ngoc Doan Trinh | E43: =VLOOKUP(B43,VN_Emails!B:H,7,0) -> Senior Merchandise | F43: AMMAVNMPC000044 | G43: =SUBSTITUTE(VLOOKUP(B43,VN_Emails!B:H,2,0),"@mapactive.vn","") -> trinh.tranngocdoan | H43: Office | I43: =J43&" "&K43&" "&L43 -> Laptop Dell Latitude 3520 | J43: Laptop | K43: Dell | L43: Latitude 3520 | M43: BGBJGL3 | N43: 16 | O43: 256 | P43: SSD | Q43: 1400 MHz 11th Gen Intel Core i5-1135G7 @ 2.40GHz | X43: MMA-LAP-0044 | Y43: DONE | Z43: DONE | AA43: DONE | AB43: DONE
A44: =A43+1 -> #REF! | B44: 22VN00000045 | C44: Available | D44: =VLOOKUP(B44,VN_Emails!B:H,4,0) -> #N/A | E44: =VLOOKUP(B44,VN_Emails!B:H,7,0) -> #N/A | F44: AMMAVNOPC000045 | G44: =SUBSTITUTE(VLOOKUP(B44,VN_Emails!B:H,2,0),"@mapactive.vn","") -> #N/A | H44: Office | I44: =J44&" "&K44&" "&L44 -> Laptop Dell Latitude 7490 | J44: Laptop | K44: Dell | L44: Latitude 7490 | M44: 8DBRMV2 | N44: 16 | O44: 256 | P44: SSD | Q44: 1900 MHz Core i5-8350U | T44: 30/08/2023 Anh Trí OP bàn giao máy ,setup cho nhân viên mới 1. Võ Thị Hoàng Ánh Xuân – Operations Executive – Operations Department – On board 19/10/2023 | V44: - Trí OM (bàn giao cho IT ngày 30/08/2023 | X44: MMA-LAP-0045 | Y44: DONE | Z44: DONE | AA44: DONE | AB44: DONE
A45: =A44+1 -> #REF! | B45: 22VN00000046 | C45: Available | D45: =VLOOKUP(B45,VN_Emails!B:H,4,0) -> #N/A | E45: =VLOOKUP(B45,VN_Emails!B:H,7,0) -> #N/A | F45: AMMAVNMDC000046 | G45: =SUBSTITUTE(VLOOKUP(B45,VN_Emails!B:H,2,0),"@mapactive.vn","") -> #N/A | H45: Office | I45: =J45&" "&K45&" "&L45 -> Laptop HP Pavilion 15-eg0xxx | J45: Laptop | K45: HP | L45: Pavilion 15-eg0xxx | M45: 5CD108K0PN | N45: 12 | O45: 256 | P45: SSD | Q45: 3000 MHz 11th Gen Intel Core i3-1115G4 @ 3.00GHz | T45: máy cũ Đăng | X45: MMA-LAP-0046 | Y45: DONE | Z45: DONE | AA45: DONE | AB45: DONE
A46: =A45+1 -> #REF! | B46: 22VN00000047 | C46: Available | D46: =VLOOKUP(B46,VN_Emails!B:H,4,0) -> #N/A | E46: =VLOOKUP(B46,VN_Emails!B:H,7,0) -> #N/A | F46: AMMAVNOPC000047 | G46: =SUBSTITUTE(VLOOKUP(B46,VN_Emails!B:H,2,0),"@mapactive.vn","") -> #N/A | H46: Office | I46: =J46&" "&K46&" "&L46 -> Laptop Dell Latitude 5420 | J46: Laptop | K46: Dell | L46: Latitude 5420 | M46: 1BXCZH3 | N46: 16 | O46: 512 | P46: SSD | Q46: 1400 MHz 11th Gen Intel Core i5-1135G7 @ 2.40GHz | T46: Máy HỒ HẢI ĐĂNG BÀN GIAO NGÀY 14/11/23 | W46: DISABLE | X46: MMA-LAP-0047 | Y46: Need to do both | AA46: DONE | AB46: DONE | AC46: DONE
A47: =A46+1 -> #REF! | B47: 22VN00000048 | C47: In Use | D47: IT BACKUP | E47: =VLOOKUP(B47,VN_Emails!B:H,7,0) -> #N/A | F47: AMMAVNITC000048 change to ZV37-ADMIN | H47: Office | I47: =J47&" "&K47&" "&L47 -> Laptop Lenovo ThinkPad E490 | J47: Laptop | K47: Lenovo | L47: ThinkPad E490 | M47: PF1JT4Q6 | N47: 8 | O47: 500 | P47: SSD | Q47: 1800 MHz Core i5-8265U | T47: - Máy cũ của Quỳnh AM HN, IT ĐÃ THAY SSD 500GB - 13-Nov-2023: gửi đi sửa USB, bản lề, phím change hostname to zv35 | V47: Máy của Quỳnh Am bị hư ổ cứng nên trả máy về cho IT, CHO TUYỀN MD MƯỢN SỬ DỤNG TẠM | X47: MMA-LAP-0048 | Y47: DONE | Z47: DONE | AA47: DONE | AB47: DONE
A48: =A47+1 -> #REF! | B48: 22VN00000049 | C48: Available | D48: =VLOOKUP(B48,VN_Emails!B:H,4,0) -> #N/A | E48: =VLOOKUP(B48,VN_Emails!B:H,7,0) -> #N/A | F48: AMMAVNMDC000049 | G48: =SUBSTITUTE(VLOOKUP(B48,VN_Emails!B:H,2,0),"@mapactive.vn","") -> #N/A | H48: Office | I48: =J48&" "&K48&" "&L48 -> Laptop Dell Latitude 3520 | J48: Laptop | K48: Dell | L48: Latitude 3520 | M48: 6R4JGL3 | N48: 8 | O48: 256 | P48: SSD | Q48: 1400 MHz 11th Gen Intel Core i5-1135G7 @ 2.40GHz | X48: MMA-LAP-0049 | Y48: DONE | Z48: DONE | AA48: DONE | AB48: DONE
A49: =A48+1 -> #REF! | B49: 22VN00000050 | C49: In Use | D49: =VLOOKUP(B49,VN_Emails!B:H,4,0) -> Duong Quang Minh Tuan | E49: Nghia old laptop (reserved for Duong Quang Minh Tuan) | F49: AMMAVNITC000050 | G49: =SUBSTITUTE(VLOOKUP(B49,VN_Emails!B:H,2,0),"@mapactive.vn","") -> tuan.duongquangminh | H49: Office | I49: =J49&" "&K49&" "&L49 -> Laptop Dell Latitude 5430 | J49: Laptop | K49: Dell | L49: Latitude 5430 | M49: 9NN2SQ3 | N49: 16 | O49: 512 | P49: SSD | Q49: 2500 MHz 12th Gen Intel Core i5-1235U | T49: Đã bảo hành, thay SSD và cài Win 11 & update driver full | V49: THOI HUU NGHIA (PnD) OLD LAPTOP Thu hồi laptop 3520 và bàn giao laptop 5430 của Nghĩa PJ cho Dương Quang Minh Tuấn Op | X49: MMA-LAP-0050 | Y49: DONE | Z49: DONE | AA49: DONE | AB49: DONE
A50: =A49+1 -> #REF! | B50: 22VN00000051 | C50: In Use | D50: =VLOOKUP(B50,VN_Emails!B:H,4,0) -> Nguyen Thi Huynh Mai | E50: =VLOOKUP(B50,VN_Emails!B:H,7,0) -> Finance, Tax & Accounting Manager | F50: AMMAVNACC000051 | G50: mai.nguyenthihuynh | H50: Office | I50: =J50&" "&K50&" "&L50 -> Laptop Dell Latitude 5420 | J50: Laptop | K50: Dell | L50: Latitude 5420 | M50: 66XN2F3 | N50: 16 | O50: 1024 | P50: SSD | Q50: 1400 MHz 11th Gen Intel Core i5-1135G7 @ 2.40GHz | T50: Đã cài lại win 10 và bàn giao cho chị Maya | V50: Huynh Ngoc Son old laptop (reserved for Ms. Maya) | X50: MMA-LAP-0051 | Y50: DONE | Z50: DONE | AA50: DONE | AB50: DONE
A51: =A50+1 -> #REF! | B51: 22VN00000075 | C51: Available | D51: =VLOOKUP(B51,VN_Emails!B:H,4,0) -> #N/A | E51: =VLOOKUP(B51,VN_Emails!B:H,7,0) -> #N/A | F51: AMMAVNPDC000052 | G51: =SUBSTITUTE(VLOOKUP(B51,VN_Emails!B:H,2,0),"@mapactive.vn","") -> #N/A | H51: Office | I51: =J51&" "&K51&" "&L51 -> Laptop Dell Latitude 5430 | J51: Laptop | K51: Dell | L51: Latitude 5430 | M51: 61N8RQ3 | N51: 16 | O51: 512 | P51: SSD | Q51: 2500 MHz 12th Gen Intel Core i5-1235U | T51: 19/04/2024 tra.truongvantin resigned | V51: tra.truongvantin | X51: MMA-LAP-0052 | Y51: DONE | Z51: DONE | AA51: DONE | AB51: DONE
A52: =A51+1 -> #REF! | B52: 22VN00000053 | C52: In Use | D52: =VLOOKUP(B52,VN_Emails!B:H,4,0) -> Vo Lam Minh Dat | E52: =VLOOKUP(B52,VN_Emails!B:H,7,0) -> Area Manager (South) | F52: AMMAVNWSC000053 | G52: =SUBSTITUTE(VLOOKUP(B52,VN_Emails!B:H,2,0),"@mapactive.vn","") -> dat.volamminh | H52: Office | I52: =J52&" "&K52&" "&L52 -> Laptop Dell Latitude 5430 | J52: Laptop | K52: Dell | L52: Latitude 5430 | M52: 4BH2SQ3 | N52: 16 | O52: 512 | P52: SSD | Q52: 2500 MHz 12th Gen Intel Core i5-1235U | X52: MMA-LAP-0053 | Y52: DONE | AA52: DONE | AB52: DONE
A53: =A52+1 -> #REF! | B53: 22VN00000054 | C53: In Use | D53: =VLOOKUP(B53,VN_Emails!B:H,4,0) -> Ngo Anh Tuan | E53: =VLOOKUP(B53,VN_Emails!B:H,7,0) -> Senior Wholesaler | F53: AMMAVNWSC000054 | G53: =SUBSTITUTE(VLOOKUP(B53,VN_Emails!B:H,2,0),"@mapactive.vn","") -> tuan.ngoanh | H53: Office | I53: =J53&" "&K53&" "&L53 -> Laptop Dell Latitude 3520 | J53: Laptop | K53: Dell | L53: Latitude 3520 | M53: DQ9VKG3 | N53: 8 | O53: 256 | P53: SSD | Q53: 2200 MHz 11th Gen Intel Core i3-1115G4 @ 3.00GHz | X53: MMA-LAP-0054 | Y53: DONE | AA53: DONE | AB53: DONE
A54: =A53+1 -> #REF! | B54: 22VN00000055 | C54: Available | D54: =VLOOKUP(B54,VN_Emails!B:H,4,0) -> #N/A | E54: =VLOOKUP(B54,VN_Emails!B:H,7,0) -> #N/A | F54: AMMAVNWSC000055 | G54: =SUBSTITUTE(VLOOKUP(B54,VN_Emails!B:H,2,0),"@mapactive.vn","") -> #N/A | H54: Office | I54: =J54&" "&K54&" "&L54 -> Laptop Dell Latitude 3520 | J54: Laptop | K54: Dell | L54: Latitude 3520 | M54: FR8VKG3 | N54: 8 | O54: 256 | P54: SSD | Q54: 2200 MHz 11th Gen Intel Core i3-1115G4 @ 3.00GHz | X54: MMA-LAP-0055 | Y54: DONE | AA54: DONE | AB54: DONE
A55: =A54+1 -> #REF! | B55: 22VN00000056 | C55: Available | D55: =VLOOKUP(B55,VN_Emails!B:H,4,0) -> #N/A | E55: =VLOOKUP(B55,VN_Emails!B:H,7,0) -> #N/A | F55: AMMAVNWSC000056 | G55: =SUBSTITUTE(VLOOKUP(B55,VN_Emails!B:H,2,0),"@mapactive.vn","") -> #N/A | H55: Office | I55: =J55&" "&K55&" "&L55 -> Laptop Dell Latitude 3520 | J55: Laptop | K55: Dell | L55: Latitude 3520 | M55: CR8VKG3 | N55: 8 | O55: 256 | P55: SSD | Q55: 2200 MHz 11th Gen Intel Core i3-1115G4 @ 3.00GHz | X55: MMA-LAP-0056 | Y55: DONE | AA55: DONE | AB55: DONE
A56: =A55+1 -> #REF! | B56: 22VN00000057 | C56: Available | D56: =VLOOKUP(B56,VN_Emails!B:H,4,0) -> #N/A | E56: =VLOOKUP(B56,VN_Emails!B:H,7,0) -> #N/A | F56: AMMAVNWSC000057 | G56: =SUBSTITUTE(VLOOKUP(B56,VN_Emails!B:H,2,0),"@mapactive.vn","") -> #N/A | H56: Office | I56: =J56&" "&K56&" "&L56 -> Laptop Dell Latitude 3520 | J56: Laptop | K56: Dell | L56: Latitude 3520 | M56: 2R9VKG3 | N56: 8 | O56: 256 | P56: SSD | Q56: 2200 MHz 11th Gen Intel Core i3-1115G4 @ 3.00GHz | X56: MMA-LAP-0057 | Y56: DONE | AA56: DONE | AB56: DONE
A57: =A56+1 -> #REF! | B57: 22VN00000058 | C57: Available | F57: AMMAVNECC000058 | G57: =SUBSTITUTE(VLOOKUP(B57,VN_Emails!B:H,2,0),"@mapactive.vn","") -> #N/A | H57: Office | I57: =J57&" "&K57&" "&L57 -> Laptop Dell Latitude 5420 | J57: Laptop | K57: Dell | L57: Latitude 5420 | M57: C3KCZH3 | N57: 16 | O57: 512 | P57: SSD | Q57: 1400 MHz 11th Gen Intel Core i5-1135G7 @ 2.40GHz | X57: MMA-LAP-0058 | Y57: DONE | Z57: DONE | AA57: DONE | AB57: DONE
A58: =A57+1 -> #REF! | B58: 22VN00000059 | C58: In Use | D58: =VLOOKUP(B58,VN_Emails!B:H,4,0) -> Nguyen My Binh | E58: Digital Commercial Manager | F58: AMMAVNECC000059 | G58: binh.nguyenmy | H58: Office | I58: =J58&" "&K58&" "&L58 -> Laptop Dell Latitude 5420 | J58: Laptop | K58: Dell | L58: Latitude 5420 | M58: DGGDZH3 | N58: 16 | O58: 512 | P58: SSD | Q58: 1400 MHz 11th Gen Intel Core i5-1135G7 @ 2.40GHz | T58: Anh hieu.trantrung bàn giao máy ngày 31/08/2023 ngoc.nguyenduyen Máy lỗi xuất hdmi 23/4/2024 | X58: MMA-LAP-0059 | Y58: DONE | Z58: DONE | AA58: DONE | AB58: DONE
A59: =A58+1 -> #REF! | B59: 22VN00000060 | C59: In Use | D59: Foot Locker Suppervisior(NGuyen Si Anh) | E59: Foot Locker Suppervisior | F59: AMMAVNOPC000060 | H59: Office | I59: =J59&" "&K59&" "&L59 -> Laptop Lenovo Thinkpad X280 | J59: Laptop | K59: Lenovo | L59: Thinkpad X280 | M59: PC0UQCVY | N59: 8 | O59: 256 | P59: SSD | Q59: 1800 MHz Core i5-8250U | X59: MMA-LAP-0060 | Y59: DONE | AA59: DONE | AB59: DONE | AC59: DONE
A60: =A59+1 -> #REF! | B60: 22VN00000061 | C60: In Use | D60: =VLOOKUP(B60,VN_Emails!B:H,4,0) -> Le Ngoc My Linh | E60: =VLOOKUP(B60,VN_Emails!B:H,7,0) -> Senior Merchandise | F60: AMMAVNMDC000061 | G60: =SUBSTITUTE(VLOOKUP(B60,VN_Emails!B:H,2,0),"@mapactive.vn","") -> linh.lengocmy | H60: Office | I60: =J60&" "&K60&" "&L60 -> Laptop Dell Latitude 3520 | J60: Laptop | K60: Dell | L60: Latitude 3520 | M60: 3KZCKG3 | N60: 8 | O60: 256 | P60: SSD | Q60: 1400 MHz 11th Gen Intel Core i5-1135G7 @ 2.40GHz | X60: MMA-LAP-0061 | Y60: DONE | Z60: DONE | AA60: DONE | AB60: DONE
A61: =A60+1 -> #REF! | B61: 22VN00000062 | C61: In Use | D61: =VLOOKUP(B61,VN_Emails!B:H,4,0) -> Ngo Tieu Binh | E61: =VLOOKUP(B61,VN_Emails!B:H,7,0) -> HR Executive | F61: AMMAVNPDC000062 | G61: =SUBSTITUTE(VLOOKUP(B61,VN_Emails!B:H,2,0),"@mapactive.vn","") -> binh.ngotieu | H61: Office | I61: =J61&" "&K61&" "&L61 -> Laptop Dell Latitude 3520 | J61: Laptop | K61: Dell | L61: Latitude 3520 | M61: 71GCGG3 | N61: 16 | O61: 256 | P61: SSD | Q61: 1400 MHz 11th Gen Intel Core i5-1135G7 @ 2.40GHz | T61: loan.nguyenhoang@mapactive.vn resigned 10/5/24 | X61: MMA-LAP-0062 | Y61: DONE | Z61: DONE | AA61: DONE | AB61: DONE
A62: =A61+1 -> #REF! | B62: 22VN00000063 | C62: In Use | D62: =VLOOKUP(B62,VN_Emails!B:H,4,0) -> Ta Quynh Trang | E62: =VLOOKUP(B62,VN_Emails!B:H,7,0) -> COE Officer | F62: AMMAVNCEC000063 | G62: =SUBSTITUTE(VLOOKUP(B62,VN_Emails!B:H,2,0),"@mapactive.vn","") -> trang.taquynh | H62: Office | I62: =J62&" "&K62&" "&L62 -> Laptop Dell Latitude 3520 | J62: Laptop | K62: Dell | L62: Latitude 3520 | M62: 9JYF7S3 | N62: 8 | O62: 256 | P62: SSD | Q62: 1400 MHz 11th Gen Intel Core i5-1135G7 @ 2.40GHz | X62: MMA-LAP-0063 | Y62: DONE | Z62: DONE | AA62: DONE | AB62: DONE
A63: =A62+1 -> #REF! | B63: 22VN00000064 | C63: Available | D63: =VLOOKUP(B63,VN_Emails!B:H,4,0) -> #N/A | E63: =VLOOKUP(B63,VN_Emails!B:H,7,0) -> #N/A | F63: AMMAVNOPC000064 | G63: =SUBSTITUTE(VLOOKUP(B63,VN_Emails!B:H,2,0),"@mapactive.vn","") -> #N/A | H63: Office | I63: =J63&" "&K63&" "&L63 -> Laptop Dell Latitude 5430 | J63: Laptop | K63: Dell | L63: Latitude 5430 | M63: B8972T3 | N63: 16 | O63: 512 | P63: SSD | Q63: 2500 MHz 12th Gen Intel Core i5-1235U | T63: Hiếu IT giữ, hư touchpad | V63: Nguyễn Thị Hải Đường off 23/06/2023 , Trần Thị Kim Tuyết off 14/06/2024 | X63: MMA-LAP-0064 | Y63: DONE | AA63: DONE | AB63: DONE
A64: =A63+1 -> #REF! | B64: 22VN00000065 | C64: In Use | D64: =VLOOKUP(B64,VN_Emails!B:H,4,0) -> Nguyen Phuong Lan | E64: =VLOOKUP(B64,VN_Emails!B:H,7,0) -> Legal Manager | F64: AMMAVNLEC000065 | G64: =SUBSTITUTE(VLOOKUP(B64,VN_Emails!B:H,2,0),"@mapactive.vn","") -> lan.nguyenphuong | H64: Office | I64: =J64&" "&K64&" "&L64 -> Laptop Dell Latitude 5430 | J64: Laptop | K64: Dell | L64: Latitude 5430 | M64: 42V72T3 | N64: 16 | O64: 512 | P64: SSD | Q64: 2500 MHz 12th Gen Intel Core i5-1235U | W64: use USB token | X64: MMA-LAP-0065 | Y64: DONE | Z64: DONE | AA64: DONE | AB64: DONE
A65: =A64+1 -> #REF! | B65: 22VN00000066 | C65: In Use | D65: =VLOOKUP(B65,VN_Emails!B:H,4,0) -> Duong Thi Bao Tram | E65: =VLOOKUP(B65,VN_Emails!B:H,7,0) -> Wholesale Admin | F65: AMMAVNLOC000066 | G65: =SUBSTITUTE(VLOOKUP(B65,VN_Emails!B:H,2,0),"@mapactive.vn","") -> tram.duongthibao | H65: Office | I65: =J65&" "&K65&" "&L65 -> Laptop Dell Latitude 3520 | J65: Laptop | K65: Dell | L65: Latitude 3520 | M65: JWZF7S3 | N65: 8 | O65: 256 | P65: SSD | Q65: 1400 MHz 11th Gen Intel Core i5-1135G7 @ 2.40GHz | X65: MMA-LAP-0066 | Y65: DONE | Z65: DONE | AA65: DONE | AB65: DONE
A66: =A65+1 -> #REF! | B66: 22VN00000067 | C66: In Use | D66: =VLOOKUP(B66,VN_Emails!B:H,4,0) -> Le Ngoc Bao Minh | E66: =VLOOKUP(B66,VN_Emails!B:H,7,0) -> Risk Management & Business Process | F66: AMMAVNMDC000067 | G66: =SUBSTITUTE(VLOOKUP(B66,VN_Emails!B:H,2,0),"@mapactive.vn","") -> minh.lengocbao | H66: Office | I66: =J66&" "&K66&" "&L66 -> Laptop HP ProBook 440 G9 | J66: Laptop | K66: HP | L66: ProBook 440 G9 | M66: 5CD250F9YL | N66: 16 | O66: 512 | P66: SSD | Q66: 2500 MHz 12th Gen Intel Core i5-1235U | X66: MMA-LAP-0067 | Y66: DONE | Z66: DONE | AA66: DONE | AB66: DONE | AC66: DONE
A67: =A81+1 -> #REF! | B67: 22VN00000069 | C67: Available | D67: =VLOOKUP(B67,VN_Emails!B:H,4,0) -> #N/A | E67: =VLOOKUP(B67,VN_Emails!B:H,7,0) -> #N/A | F67: AMMAVNITC000069 | G67: =SUBSTITUTE(VLOOKUP(B67,VN_Emails!B:H,2,0),"@mapactive.vn","") -> #N/A | H67: Office | I67: =J67&" "&K67&" "&L67 -> Laptop Dell Latitude 3520 | J67: Laptop | K67: Dell | L67: Latitude 3520 | M67: 3DYF7S3 | N67: 12 | O67: 256 | P67: SSD | Q67: 1400 MHz 11th Gen Intel Core i5-1135G7 @ 2.40GHz | X67: MMA-LAP-0069 | Y67: DONE | Z67: DONE | AA67: DONE | AB67: DONE
A68: =A67+1 -> #REF! | B68: 22VN00000070 | C68: In Use | D68: =VLOOKUP(B68,VN_Emails!B:H,4,0) -> Nguyen Thi Qui | E68: =VLOOKUP(B68,VN_Emails!B:H,7,0) -> General Accountant UFO | F68: AMMAVNACC000070 | G68: =SUBSTITUTE(VLOOKUP(B68,VN_Emails!B:H,2,0),"@mapactive.vn","") -> qui.nguyenthi | H68: Office | I68: =J68&" "&K68&" "&L68 -> Laptop Dell Latitude 5430 | J68: Laptop | K68: Dell | L68: Latitude 5430 | M68: H3NVHW3 | N68: 16 | O68: 512 | P68: SSD | Q68: 2500 MHz 12th Gen Intel Core i5-1235U | W68: use USB token | X68: MMA-LAP-0070 | Y68: DONE | Z68: DONE | AA68: DONE | AB68: DONE
A69: =A68+1 -> #REF! | B69: 22VN00000071 | C69: Available | D69: =VLOOKUP(B69,VN_Emails!B:H,4,0) -> #N/A | E69: =VLOOKUP(B69,VN_Emails!B:H,7,0) -> #N/A | F69: AMMAVNITC000071 | G69: =SUBSTITUTE(VLOOKUP(B69,VN_Emails!B:H,2,0),"@mapactive.vn","") -> #N/A | H69: Office | I69: =J69&" "&K69&" "&L69 -> Laptop Dell Latitude 5430 | J69: Laptop | K69: Dell | L69: Latitude 5430 | M69: BJ972T3 | N69: 16 | O69: 512 | P69: SSD | Q69: 2500 MHz 12th Gen Intel Core i5-1235U | T69: Máy của a AN(IT) Đổi ổ cứng vs XX81 (Máy A huy) | X69: MMA-LAP-0071 | Y69: DONE | Z69: DONE | AA69: DONE | AB69: DONE
A70: =A69+1 -> #REF! | B70: 22VN00000072 | C70: In Use | D70: =VLOOKUP(B70,VN_Emails!B:H,4,0) -> Dao Thi Hong Le | E70: =VLOOKUP(B70,VN_Emails!B:H,7,0) -> Training Assistant Manager | F70: AMMAVNTAC000072 | G70: =SUBSTITUTE(VLOOKUP(B70,VN_Emails!B:H,2,0),"@mapactive.vn","") -> le.daothihong | H70: Office | I70: =J70&" "&K70&" "&L70 -> Laptop Dell Latitude 5430 | J70: Laptop | K70: Dell | L70: Latitude 5430 | M70: 1KHVHW3 | N70: 16 | O70: 512 | P70: SSD | Q70: 2500 MHz 12th Gen Intel Core i5-1235U | X70: MMA-LAP-0072 | Y70: DONE | Z70: DONE | AA70: DONE | AB70: DONE
A71: =A70+1 -> #REF! | B71: 22VN00000073 | C71: In Use | D71: =VLOOKUP(B71,VN_Emails!B:H,4,0) -> Nguyen Quoc Huy | E71: =VLOOKUP(B71,VN_Emails!B:H,7,0) -> Visual Merchandise Supervisor | F71: AMMAVNMDC000073 | G71: =SUBSTITUTE(VLOOKUP(B71,VN_Emails!B:H,2,0),"@mapactive.vn","") -> huy.nguyenquoc | H71: Office | I71: =J71&" "&K71&" "&L71 -> Laptop Dell Latitude 5430 | J71: Laptop | K71: Dell | L71: Latitude 5430 | M71: 7X82HW3 | N71: 16 | O71: 512 | P71: SSD | Q71: 2500 MHz 12th Gen Intel Core i5-1235U | X71: MMA-LAP-0073 | Y71: DONE | Z71: DONE | AA71: DONE | AB71: DONE
A72: =A71+1 -> #REF! | B72: 22VN00000074 | C72: In Use | D72: =VLOOKUP(B72,VN_Emails!B:H,4,0) -> Nguyen Thanh Hai | E72: =VLOOKUP(B72,VN_Emails!B:H,7,0) -> Intern | F72: AMMAVNMRC000074 | G72: =SUBSTITUTE(VLOOKUP(B72,VN_Emails!B:H,2,0),"@mapactive.vn","") -> hai.nguyenthanh | H72: Office | I72: =J72&" "&K72&" "&L72 -> Laptop Lenovo Thinkpad X280 | J72: Laptop | K72: Lenovo | L72: Thinkpad X280 | M72: PC0VT5R5 | N72: 8 | O72: 256 | P72: SSD | Q72: INTEL (R) CORE (TM) I5-8250U 1.60GHZ (8CPUS) | T72: Sóng Nam nhận máy về kiểm tra và báo giá chi phí sửa màn hình bị giật 29-01-2024 | V72: - Pham Thi My Dung quit job 02/10/2023 -Lê Ngọc Bích Trâm – Marketing Supervisor – Marketing Department (Foot Locker) – On board 20/10/2023 > Gửi sóng nam sửa màn hình bị giật khung hình 29-01-24> done | X72: MMA-LAP-0074 | Y72: DONE | Z72: DONE | AA72: DONE | AB72: DONE
A73: =A72+1 -> #REF! | B73: 22VN00000052 | C73: In Use | D73: =VLOOKUP(B73,VN_Emails!B:H,4,0) -> Vo Thi Hoang Anh Xuan | E73: Laptop Quynh AM (resigned) | F73: AMMAVNOPC000075 | G73: =SUBSTITUTE(VLOOKUP(B73,VN_Emails!B:H,2,0),"@mapactive.vn","") -> xuan.vothihoanganh | H73: Office | I73: =J73&" "&K73&" "&L73 -> Laptop Dell Latitude 5430 | J73: Laptop | K73: Dell | L73: Latitude 5430 | M73: 2NS0HW3 | N73: 16 | O73: 512 | P73: SSD | Q73: 2500 MHz 12th Gen Intel Core i5-1235U | V73: Quynh.nguyennhu resigned | X73: MMA-LAP-0075 | Y73: DONE | AA73: DONE | AB73: DONE
A74: =A73+1 -> #REF! | B74: 22VN00000076 | C74: In Use | D74: =VLOOKUP(B74,VN_Emails!B:H,4,0) -> Le Thi Anh Tuyet | E74: =VLOOKUP(B74,VN_Emails!B:H,7,0) -> Tax & Accounting Assistant Manager | F74: AMMAVNECC000076 | G74: =SUBSTITUTE(VLOOKUP(B74,VN_Emails!B:H,2,0),"@mapactive.vn","") -> tuyet.lethianh | H74: Office | I74: =J74&" "&K74&" "&L74 -> Laptop Dell Latitude 5430 | J74: Laptop | K74: Dell | L74: Latitude 5430 | M74: CXJ8VV3 | N74: 16 | O74: 512 | P74: SSD | Q74: 2500 MHz 12th Gen Intel Core i5-1235U | X74: MMA-LAP-0076 | Y74: DONE | Z74: DONE | AA74: DONE | AB74: DONE
A75: =A74+1 -> #REF! | B75: 22VN00000077 | C75: In Use | D75: Tran Vu Kim Chi | E75: =VLOOKUP(B75,VN_Emails!B:H,7,0) -> Brand Division Manager (Foot Locker) | F75: AMMAVNMDC000077 | G75: chi.tranvukim | H75: Office | I75: =J75&" "&K75&" "&L75 -> Laptop Dell Latitude 5430 | J75: Laptop | K75: Dell | L75: Latitude 5430 | M75: 6MS0HW3 | N75: 16 | O75: 512 | P75: SSD | Q75: 2500 MHz 12th Gen Intel Core i5-1235U | V75: laptop cũ Nguyễn Đỗ Hiền đã bàn giaocho IT ngay7/02/14 Cho Trần Vũ Kim Chi Mượn máy ngày 07/02/2024 | X75: MMA-LAP-0077 | Y75: DONE | Z75: DONE | AA75: DONE | AB75: DONE
A76: =A75+1 -> #REF! | B76: 22VN00000078 | C76: In Use | D76: =VLOOKUP(B76,VN_Emails!B:H,4,0) -> Nguyen Ngoc Lan Anh | E76: =VLOOKUP(B76,VN_Emails!B:H,7,0) -> Graphic Designer | F76: AMMAVNGDC000078 | G76: =SUBSTITUTE(VLOOKUP(B76,VN_Emails!B:H,2,0),"@mapactive.vn","") -> anh.nguyenngoclan | H76: Office | I76: =J76&" "&K76&" "&L76 -> Laptop Dell G15 5520 | J76: Laptop | K76: Dell | L76: G15 5520 | M76: 9R2B9T3 | N76: 32 | O76: 512 | P76: SSD | Q76: 12TH GEN INTEL CORE I7-12700H(20CPU)2.3GHZ SSD512GB-GEFORCE GTX 3060 | X76: MMA-LAP-0078 | Y76: DONE | Z76: DONE | AA76: DONE | AB76: DONE
A77: =A76+1 -> #REF! | B77: 22VN00000079 | C77: In Use | D77: =VLOOKUP(B77,VN_Emails!B:H,4,0) -> Le Thanh Duyen | E77: =VLOOKUP(B77,VN_Emails!B:H,7,0) -> Graphic Designer (Foot Locker) | F77: AMMAVNGDD000079 | G77: =SUBSTITUTE(VLOOKUP(B77,VN_Emails!B:H,2,0),"@mapactive.vn","") -> duyen.lethanh | H77: Office | I77: =J77&" "&K77&" "&L77 -> Desktop HP Pavilion 590-p0xxx | J77: Desktop | K77: HP | L77: Pavilion 590-p0xxx | M77: 8CG824CV0T | N77: 8 | O77: 1512 | P77: HDD (1 TB) SSD (512 GB) | Q77: 2800 MHz Core i5-8400 HDD 1TB-SSD 240GB | V77: - NGUYỄN NGỌC LAN ANH (Sophie) - Lê Thanh Duyên | X77: MMA-DES-0001 | Y77: DONE | Z77: DONE | AA77: DONE | AB77: DONE
A78: =A77+1 -> #REF! | B78: 22VN00000080 | C78: In Use | D78: =VLOOKUP(B78,VN_Emails!B:H,4,0) -> Nguyen Thanh Anh Thu | E78: =VLOOKUP(B78,VN_Emails!B:H,7,0) -> Visual Merchandise Manager | F78: AMMAVNMDC000080 | G78: =SUBSTITUTE(VLOOKUP(B78,VN_Emails!B:H,2,0),"@mapactive.vn","") -> thu.nguyenthanhanh | H78: Office | I78: =J78&" "&K78&" "&L78 -> Laptop Dell G15 5520 | J78: Laptop | K78: Dell | L78: G15 5520 | M78: FLQ85R3 | N78: 16 | O78: 1000 | P78: SSD | Q78: 12TH GEN INTEL CORE I7-12700H(20CPU)2.3GHZ SSD512GB-GEFORCE GTX 2050TI | X78: MMA-LAP-0079 | Y78: DONE | Z78: DONE | AA78: DONE | AB78: DONE
A79: =A78+1 -> #REF! | B79: 22VN00000081 | C79: In Use | D79: =VLOOKUP(B79,VN_Emails!B:H,4,0) -> Dao Duc Huy | E79: =VLOOKUP(B79,VN_Emails!B:H,7,0) -> Area Manager (South) | F79: AMMAVNOPC000081 | G79: =SUBSTITUTE(VLOOKUP(B79,VN_Emails!B:H,2,0),"@mapactive.vn","") -> Huy.daoduc | H79: Office | I79: =J79&" "&K79&" "&L79 -> Laptop Dell Latitude 5430 | J79: Laptop | K79: Dell | L79: Latitude 5430 | M79: F598VV3 | N79: 16 | O79: 512 | P79: SSD | Q79: 2500 MHz 12th Gen Intel Core i5-1235U | V79: Hư swap với máy a an(71) | X79: MMA-LAP-0080 | Y79: DONE | Z79: DONE | AA79: DONE | AB79: DONE
A80: =A79+1 -> #REF! | B80: 22VN00000082 | C80: Available | E80: =VLOOKUP(B80,VN_Emails!B:H,7,0) -> #N/A | F80: AMMAVNMDC000082 | G80: =SUBSTITUTE(VLOOKUP(B80,VN_Emails!B:H,2,0),"@mapactive.vn","") -> #N/A | H80: Office | I80: =J80&" "&K80&" "&L80 -> Laptop Dell Latitude 3520 | J80: Laptop | K80: Dell | L80: Latitude 3520 | M80: DL0G7S3 | N80: 8 | O80: 512 | P80: SSD | Q80: 11TH Gen Intel ® Core™ i5-1135G7 @2.40Ghz | X80: MMA-LAP-0081 | Y80: DONE | Z80: DONE | AA80: DONE | AB80: DONE
A81: =A66+1 -> #REF! | B81: 22VN00000068 | C81: Available | D81: =VLOOKUP(B81,VN_Emails!B:H,4,0) -> #N/A | E81: =VLOOKUP(B81,VN_Emails!B:H,7,0) -> #N/A | F81: AMMAVNMPC000068 | G81: =SUBSTITUTE(VLOOKUP(B81,VN_Emails!B:H,2,0),"@mapactive.vn","") -> #N/A | H81: Office | I81: =J81&" "&K81&" "&L81 -> Laptop Dell Latitude 3520 | J81: Laptop | K81: Dell | L81: Latitude 3520 | M81: 6SYF7S3 | N81: 8 | O81: 256 | P81: SSD | Q81: 1400 MHz 11th Gen Intel Core i5-1135G7 @ 2.40GHz | T81: - 13/5/24 Vo Thi Hoang Anh Xuan OPSCCTV - Cấp cho Vân sale(máy chị ấy bị hở bản lề) | V81: - Tran Thi Toan My reassigned - 13/5/24 Vo Thi Hoang Anh Xuan OPSCCTV | X81: MMA-LAP-0068 | Y81: DONE | Z81: DONE | AA81: DONE | AB81: DONE | AD81: Plan as the last resort for NB Diamond (faulty HDD)
A82: =A80+1 -> #REF! | B82: 22VN00000083 | C82: Available | D82: =VLOOKUP(B82,VN_Emails!B:H,4,0) -> #N/A | E82: =VLOOKUP(B82,VN_Emails!B:H,7,0) -> #N/A | F82: AMMAVNMPC000083 | G82: =SUBSTITUTE(VLOOKUP(B82,VN_Emails!B:H,2,0),"@mapactive.vn","") -> #N/A | H82: Office | I82: =J82&" "&K82&" "&L82 -> Laptop Dell Latitude 3520 | J82: Laptop | K82: Dell | L82: Latitude 3520 | M82: 5YSSKS3 | N82: 8 | O82: 256 | P82: SSD | Q82: 3000 MHz 11th Gen Intel Core i3-1115G4 @ 3.00GHz | T82: nhung.nguyenthituyet resigned | X82: MMA-LAP-0082 | Y82: DONE | Z82: DONE | AA82: DONE | AB82: DONE
A83: =A82+1 -> #REF! | B83: 22VN00000084 | C83: Available | D83: =VLOOKUP(B83,VN_Emails!B:H,4,0) -> #N/A | E83: =VLOOKUP(B83,VN_Emails!B:H,7,0) -> #N/A | F83: AMMAVNTAC000084 | G83: =SUBSTITUTE(VLOOKUP(B83,VN_Emails!B:H,2,0),"@mapactive.vn","") -> #N/A | H83: Office | I83: =J83&" "&K83&" "&L83 -> Laptop Dell Latitude 3520 | J83: Laptop | K83: Dell | L83: Latitude 3520 | M83: BXSSKS3 | N83: 8 | O83: 256 | P83: SSD | Q83: 3000 MHz 11th Gen Intel Core i3-1115G4 @ 3.00GHz | T83: Luong resigned | X83: MMA-LAP-0083 | Y83: DONE | Z83: DONE | AA83: DONE | AB83: DONE
A84: =#REF!+1 -> #REF! | B84: 22VN00000086 | C84: In Use | D84: Nguyen Ha Phuong Uyen | E84: Nguyen Nhu Quynh (Brand Manager Bata) old laptop | F84: AMMAVNMDC000086 | G84: uyen.nguyenhaphuong | H84: Office | I84: =J84&" "&K84&" "&L84 -> Laptop Dell Latitude 5430 | J84: Laptop | K84: Dell | L84: Latitude 5430 | M84: 4084RV3 | N84: 16 | O84: 512 | P84: SSD | Q84: 12th Gen Intel(R) Core(TM) i5-1235U[Cores 12 | T84: Đang cấp tạm cho chị Uyên ngày 18/03/2024 | V84: 31/01/2024 Nguyen Nhu Quynh (Brand Manager Bata) resigned | X84: MMA-LAP-0085 | Y84: DONE | Z84: DONE | AA84: DONE | AB84: DONE
A85: =A84+1 -> #REF! | B85: 22VN00000087 | C85: Available | D85: =VLOOKUP(B85,VN_Emails!B:H,4,0) -> #N/A | E85: =VLOOKUP(B85,VN_Emails!B:H,7,0) -> #N/A | F85: AMMAVNMDC000087 | G85: =SUBSTITUTE(VLOOKUP(B85,VN_Emails!B:H,2,0),"@mapactive.vn","") -> #N/A | H85: Office | I85: =J85&" "&K85&" "&L85 -> Laptop Dell Latitude 3520 | J85: Laptop | K85: Dell | L85: Latitude 3520 | M85: 2XSSKS3 | N85: 8 | O85: 256 | P85: SSD | Q85: 3000 MHz 11th Gen Intel Core i3-1115G4 @ 3.00GHz | X85: MMA-LAP-0086 | Y85: DONE | Z85: DONE | AA85: DONE | AB85: DONE
A86: =A85+1 -> #REF! | B86: 22VN00110003 | C86: Available | E86: =VLOOKUP(B86,VN_Emails!B:H,7,0) -> #N/A | F86: AMMAVNHRD000088 | G86: =SUBSTITUTE(VLOOKUP(B86,VN_Emails!B:H,2,0),"@mapactive.vn","") -> #N/A | H86: Office | I86: =J86&" "&K86&" "&L86 -> Desktop HP ProDesk 400 G3 Mini | J86: Desktop | K86: HP | L86: ProDesk 400 G3 Mini | M86: 8CG8105MSL | N86: 8 | O86: 500 | P86: SSD | Q86: Intel (R) CORE (TM) I5-7500T.2.7GHZ (4CPUS) | Y86: DONE | Z86: DONE | AA86: DONE | AB86: DONE
A87: =A86+1 -> #REF! | B87: 22VN00000089 | C87: Available | D87: Accounting Intern | E87: Accounting Intern (Le Nhi) | F87: AMMAVNACD000089 | H87: Office | I87: =J87&" "&K87&" "&L87 -> Desktop HP ProDesk 400 G3 Mini | J87: Desktop | K87: HP | L87: ProDesk 400 G3 Mini | M87: 8CG75234Q1 | N87: 8 | O87: 500 | P87: SSD | Q87: Intel (R) CORE (TM) I5-7500T.2.7GHZ (4CPUS) | T87: 25/02/2024 bàn giao intern accounting | V87: - Trước đó cấp cho Accounting Intern | Y87: DONE | Z87: DONE | AA87: DONE | AB87: DONE
A88: =#REF!+1 -> #REF! | B88: 22VN00000091 | C88: Available | E88: Marketing intern | F88: AMMAVNITC000091 | H88: Office | I88: =J88&" "&K88&" "&L88 -> Laptop Lenovo Thinkpad X280 | J88: Laptop | K88: Lenovo | L88: Thinkpad X280 | M88: PC0VT5RC | N88: 8 | O88: 256 | P88: SSD | Q88: 1800 MHz Core i5-8250U | V88: - Ni HR old laptop, CẤP TẠM CHO NGHIÊM THỊ HỒNG VÂN NGÀY 07/02/24 đã trả IT lưu kho | Y88: DONE | Z88: DONE | AA88: DONE | AB88: DONE
A89: =A88+1 -> #REF! | B89: 22VN00000092 | C89: Available | D89: =VLOOKUP(B89,VN_Emails!B:H,4,0) -> #N/A | E89: =VLOOKUP(B89,VN_Emails!B:H,7,0) -> #N/A | F89: AMMAVNMDC000092 | G89: =SUBSTITUTE(VLOOKUP(B89,VN_Emails!B:H,2,0),"@mapactive.vn","") -> #N/A | H89: Office | I89: =J89&" "&K89&" "&L89 -> Laptop Dell Latitude 5430 | J89: Laptop | K89: Dell | L89: Latitude 5430 | M89: 1GHVHW3 | N89: 16 | O89: 512 | P89: SSD | Q89: 1400 MHz 11th Gen Intel Core i5-1135G7 @ 2.40GHz | Y89: DONE | Z89: DONE | AA89: DONE | AB89: DONE
A90: =A89+1 -> #REF! | B90: 22VN00000093 | C90: In Use | D90: IT (PC-PRINTER) | E90: PC for color printing | F90: AMMAVNITD000093 | H90: Office | I90: =J90&" "&K90&" "&L90 -> Desktop DeLUX | J90: Desktop | K90: DeLUX | M90: DH67VR | N90: 16 | O90: 1024 | P90: HDD | Q90: INTEL (R) CORE (TM) I5-2400.3.1GHZ (8CPUS) | Y90: DONE | Z90: DONE | AA90: DONE | AB90: DONE
A91: =A90+1 -> #REF! | B91: 22VN00000094 | C91: In Use | D91: =VLOOKUP(B91,VN_Emails!B:H,4,0) -> Huynh Kim Ngoc Tran | E91: Intern Acc | F91: AMMAVNOPC000094 | G91: =SUBSTITUTE(VLOOKUP(B91,VN_Emails!B:H,2,0),"@mapactive.vn","") -> tran.huynhkimngoc | H91: Office | I91: =J91&" "&K91&" "&L91 -> Laptop Dell Latitude 5430 | J91: Laptop | K91: Dell | L91: Latitude 5430 | M91: 9ZHQRV3 | N91: 16 | O91: 512 | P91: SSD | Q91: 2500 MHz 12th Gen Intel Core i5-1235U | T91: Máy cũ của Thy.nguyenhoanganh 05/Dec/2024 bàn giao cho Intern Accounting\ | V91: minh.letranthien@mapactive.vn resigned thy.nguyenhoanganh resigned chi Mai giữ máy | Y91: DONE | Z91: DONE | AA91: DONE | AB91: DONE
A92: =A91+1 -> #REF! | B92: 22VN00000095 | C92: Available | D92: IT Backup | E92: Inter MKT Nguyễn Hồng Thị Minh Bình | F92: AMMAVNITC000095 | H92: Office | I92: =J92&" "&K92&" "&L92 -> Laptop Lenovo Thinkpad X280 | J92: Laptop | K92: Lenovo | L92: Thinkpad X280 | M92: PC0VSNY2 | N92: 8 | O92: 256 | P92: SSD | Q92: INTEL® CORE ™I5-8250u CPU 1.60 GhZ | T92: - 13-Nov-2023: gửi đi sửa USB, bản lề, phím - Đã sửa xong | V92: Laptop Tran Thu Huyen (AM Hai Phong) - dùng cho Supervisor Store VC03 & VE01 CHAMPION & NewEra AEON MALL HẢI PHÒNG | Y92: DONE | Z92: DONE | AA92: DONE | AB92: DONE
A93: =A92+1 -> #REF! | B93: 22VN00000096 | C93: Available | D93: IT Backup | E93: LAPTOP OLD VANHUYNHTU TRINH | F93: AMMAVNMRC000096 | G93: ` | H93: Office | I93: =J93&" "&K93&" "&L93 -> Laptop Lenovo Thinkpad X280 | J93: Laptop | K93: Lenovo | L93: Thinkpad X280 | M93: PC12PNNM | N93: 8 | O93: 256 | P93: SSD | Q93: INTEL® CORE ™I5-8250u CPU 1.60 GhZ | T93: CẦN NÂNG CẤP RAM ,laptop cũ VANHUYNHTU TRINH , bàn giao cho Nguyen Thi Phuong Dung ngày 23/11/2023, thu hồi lại ngày 01/03/2024>ITbackup | V93: LAPTOP CŨ TÚ TRINH ACC Cấp cho Dung Marketing | Y93: DONE | Z93: DONE | AA93: DONE | AB93: DONE | AC93: DONE
A94: =A93+1 -> #REF! | B94: 22VN00000097 | C94: In Use | D94: =VLOOKUP(B94,VN_Emails!B:H,4,0) -> Luu Giang Cam Van | E94: New 5430 Laptop provide Tran Vu Kim Chi – Brand Division Manager (Foot Locker) | F94: AMMAVNHRC000097 | G94: van.luugiangcam | H94: Office | I94: =J94&" "&K94&" "&L94 -> Laptop Dell Latitude 5430 | J94: Laptop | K94: Dell | L94: Latitude 5430 | M94: B1K8VV3 | N94: 16 | O94: 512 | P94: SSD | Q94: 2500 MHz 12th Gen Intel Core i5-1235U | V94: THAY CHO VICKY (HR), TRƯỚC ĐÓ MUA CHO TRẦN VŨ KIM CHI (BRND MANAGER ) | Z94: DONE | AA94: DONE | AB94: DONE | AC94: DONE
A95: =A94+1 -> #REF! | B95: 22VN00000098 | C95: In Use | D95: Mai Nguyen Diem Quynh | E95: =VLOOKUP(B95,VN_Emails!B:H,7,0) -> Payable Accountant | F95: AMMAVNACC000098 | G95: quynh.mainguyendiem | H95: Office | I95: =J95&" "&K95&" "&L95 -> Laptop Dell Latitude 3420 | J95: Laptop | K95: Dell | L95: Latitude 3420 | M95: F650FX3 | N95: 16 | O95: 512 | P95: SSD | Q95: 1400 MHz 11th Gen Intel Core i5-1135G7 @ 2.40GHz | T95: Lô 6 Laptop swap mua hàng với Cambodia | V95: Replace the old laptop of Quynh.mainguyendiem
A96: =A95+1 -> #REF! | B96: 22VN00000099 | C96: In Use | D96: =VLOOKUP(B96,VN_Emails!B:H,4,0) -> Thoi Huu Nghia | E96: new laptop 3420 provide Thoi Huu Nghia( Project team) | F96: AMMAVNPDC000099 | G96: nghia.thoihuu | H96: Office | I96: =J96&" "&K96&" "&L96 -> Laptop Dell Latitude 3420 | J96: Laptop | K96: Dell | L96: Latitude 3420 | M96: 2R20FX3 | N96: 16 | O96: 512 | P96: SSD | Q96: 1400 MHz 11th Gen Intel Core i5-1135G7 @ 2.40GHz | T96: Lô 6 Laptop swap mua hàng với Cambodia | V96: Swap old laptop of NGHIA.THOIHUU
A97: =A96+1 -> #REF! | B97: 22VN00000100 | C97: In Use | D97: =VLOOKUP(B97,VN_Emails!B:H,4,0) -> Huynh Ngoc Son | E97: Huynh Ngoc Son (Project Supervisor) | F97: AMMAVNPDC000100 | G97: son.huynhngoc | H97: Office | I97: =J97&" "&K97&" "&L97 -> Laptop Dell Latitude 3420 | J97: Laptop | K97: Dell | L97: Latitude 3420 | M97: JJNZDX3 | N97: 16 | O97: 512 | P97: SSD | Q97: 1400 MHz 11th Gen Intel Core i5-1135G7 @ 2.40GHz | T97: Lô 6 Laptop swap mua hàng với Cambodia | V97: SWAP OLD LAPTOP OF SON.HUYNHNGOC
A98: =A97+1 -> #REF! | B98: 22VN00000101 | C98: In Use | D98: =VLOOKUP(B98,VN_Emails!B:H,4,0) -> Pham My Tu | E98: =VLOOKUP(B98,VN_Emails!B:H,7,0) -> Senior Merchandise | F98: AMMAVNMDC000101 | G98: tu.phammy | H98: Office | I98: =J98&" "&K98&" "&L98 -> Laptop Dell Latitude 3420 | J98: Laptop | K98: Dell | L98: Latitude 3420 | M98: 2Q20FX3 | N98: 16 | O98: 512 | P98: SSD | Q98: 1400 MHz 11th Gen Intel Core i5-1135G7 @ 2.40GHz | T98: Lô 6 Laptop swap mua hàng với Cambodia | V98: Swap old laptop of Pham My Tu
A99: =A98+1 -> #REF! | B99: 22VN00000102 | C99: In Use | D99: =VLOOKUP(B99,VN_Emails!B:H,4,0) -> Nguyen Nam Thang | E99: =VLOOKUP(B99,VN_Emails!B:H,7,0) -> Senior Wholesaler | F99: AMMAVNITC000102 | H99: Office | I99: =J99&" "&K99&" "&L99 -> Laptop Dell Latitude 3420 | J99: Laptop | K99: Dell | L99: Latitude 3420 | M99: CY40FX3 | N99: 16 | O99: 512 | P99: SSD | Q99: 1400 MHz 11th Gen Intel Core i5-1135G7 @ 2.40GHz | T99: Lô 6 Laptop swap mua hàng với Cambodia
A100: =A99+1 -> #REF! | B100: 22VN00000103 | C100: In Use | D100: =VLOOKUP(B100,VN_Emails!B:H,4,0) -> Vo Thuy Minh Tuyen | E100: =VLOOKUP(B100,VN_Emails!B:H,7,0) -> Senior Merchandise | F100: AMMAVNLOC000103 | H100: Office | I100: =J100&" "&K100&" "&L100 -> Laptop Dell Latitude 3420 | J100: Laptop | K100: Dell | L100: Latitude 3420 | M100: 69LXDX3 | N100: 16 | O100: 512 | P100: SSD | Q100: 1400 MHz 11th Gen Intel Core i5-1135G7 @ 2.40GHz | T100: Lô 6 Laptop swap mua hàng với Cambodia | V100: Lô 6 Laptop swap mua hàng với Cambodia swap laptop of Nguyen Hoang Anh Thy
...

Sheet Warehosue mail
B1: No | C1: Email Address | D1: Full Name | E1: Display Name | F1: Hostname
B2: 1 | C2: Geodis.cs1@mapactive.vn | D2: Geodis.cs1 | E2: Geodis cs1
B3: 2 | C3: Geodis.cs2@mapactive.vn | D3: Geodis.cs2 | E3: Geodis cs2
B4: 3 | C4: Geodis.cs3@mapactive.vn | D4: Geodis.cs3 | E4: Geodis cs3
B5: 4 | C5: Geodis.inbound1@mapactive.vn | D5: Geodis.inbound1 | E5: Geodis inbound1
B6: 5 | C6: Geodis.inbound2@mapactive.vn | D6: Geodis.inbound2 | E6: Geodis inbound2
B7: 6 | C7: Geodis.outobund1@mapactive.vn | D7: Geodis.outobund1 | E7: Geodis outbound1
B8: 7 | C8: Geodis.outbound2@mapactive.vn | D8: Geodis.outbound2 | E8: Geodis outbound2

Sheet VN_Emails
A1: No. | B1: Assigned Asset | C1: Email Address | D1: Full Name | E1: Display Name | F1: English Name | G1: Department | H1: JOB TITLE | I1: O365 license | J1: Country | K1: Type | L1: Onboarding Date | M1: Request email | N1: Purchasing Request | O1: Laptop model | P1: Laptop delivery | Q1: Handover to user | R1: Notes | S1: MAP Level
A2: 1 | B2: 22VN00000086 | C2: uyen.nguyenhaphuong@mapactive.vn | D2: Nguyễn Hà Phượng Uyên | E2: Nguyen Ha Phuong Uyen | F2: Dory | G2: BOD (Finance) | H2: General Manager & Finance Controller | I2: E3 | J2: VN | K2: Office | S2: Senior General Manager
A3: 2 | B3: 22VN00000001 | C3: phung.tietnha@mapactive.vn | D3: Tiết Nhã Phụng | E3: Tiet Nha Phung | H3: Brand Manager (Converse) | I3: E3 | J3: VN | K3: Office | S3: Senior Manager
A4: 3 | B4: 22VN00000035 | C4: tam.dangthithanh@mapactive.vn | D4: Đặng Thị Thanh Tâm | E4: Dang Thi Thanh Tam | F4: Tansy | H4: Brand Manager (NB, Crocs) | I4: E3 | J4: VN | K4: Office | S4: Senior Manager
A5: 4 | B5: 22VN00000097 | C5: van.luugiangcam@mapactive.vn | D5: Lưu Giang Cẩm Vân | E5: Luu Giang Cam Van | F5: Vicky | H5: HR & Admin Manager | I5: E3 | J5: VN | K5: Office | S5: Manager
A6: 5 | B6: 22VN00000020 | C6: them.quanthanh@mapactive.vn | D6: Quan Thanh Thềm | E6: Quan Thanh Them | H6: COE Manager | I6: E3 | J6: VN | K6: Office | S6: Manager
A7: 6 | B7: 22VN00000099 | C7: nghia.thoihuu@mapactive.vn | D7: Thới Hũu Nghĩa | E7: Thoi Huu Nghia | H7: Senior Project Manager | I7: E3 | J7: VN | K7: Office | S7: Senior Manager
A8: 7 | B8: 22VN00000103 | C8: tuyen.vothuyminh@mapactive.vn | D8: Võ Thụy Minh Tuyền | E8: Vo Thuy Minh Tuyen | H8: Senior Merchandise | I8: E3 | J8: VN | K8: Office | S8: Associate Manager
A9: 8 | B9: 22VN00000101 | C9: tu.phammy@mapactive.vn | D9: Phạm Mỹ Tú | E9: Pham My Tu | H9: Senior Merchandise | I9: E3 | J9: VN | K9: Office | S9: Associate Manager
A10: 9 | B10: 22VN00000037 | C10: thanh.nguyenphuoc@mapactive.vn | D10: Nguyễn Phước Thạnh | E10: Nguyen Phuoc Thanh | H10: Merchandiser | I10: E3 | J10: VN | K10: Office | S10: Senior Executive
A11: 10 | B11: 22VN00000009 | C11: linh.lecam@mapactive.vn | D11: Lê Cẩm Linh | E11: Le Cam Linh | H11: Shipping Supervisor | I11: E3 | J11: VN | K11: Office | S11: Senior Executive
A12: 11 | B12: 22VN00000038 | C12: tram.ngothibich@mapactive.vn | D12: Ngô Thị Bích Trâm | E12: Ngo Thi Bich Tram | H12: Shipping Officer | I12: E3 | J12: VN | K12: Office | S12: Senior Associate
A13: 12 | B13: 22VN00000076 | C13: tuyet.lethianh@mapactive.vn | D13: Lê Thị Ánh Tuyết | E13: Le Thi Anh Tuyet | H13: Tax & Accounting Assistant Manager | I13: E3 | J13: VN | K13: Office | S13: Senior Associate
A14: 13 | B14: 22VN00000054 | C14: tuan.ngoanh@mapactive.vn | D14: Ngô Anh Tuấn | E14: Ngo Anh Tuan | H14: Senior Wholesaler | I14: E3 | J14: VN | K14: Office | S14: Executive
A15: 14 | B15: 22VN00000102 | C15: thang.nguyennam@mapactive.vn | D15: Nguyễn Nam Thắng | E15: Nguyen Nam Thang | H15: Senior Wholesaler | I15: E3 | J15: VN | K15: Office | S15: Executive
A16: 15 | B16: 22VN00000018 | C16: nam.dangthanh@mapactive.vn | D16: Đặng Thành Nam | E16: Dang Thanh Nam | H16: Warehouse and Distribution Supervisor | I16: E3 | J16: VN | K16: Office | S16: Senior Executive
A17: 16 | B17: 22VN00000098 | C17: quynh.mainguyendiem@mapactive.vn | D17: Mai Nguyễn Diễm Quỳnh | E17: Mai Nguyen Diem Quynh | H17: Payable Accountant | I17: E3 | J17: VN | K17: Office | S17: Senior Associate
... A25: 24 | B25: 22VN00000066 | C25: tram.duongthibao@mapactive.vn | D25: Dương Thị Bảo Trâm | E25: Duong Thi Bao Tram | H25: Wholesale Admin | I25: E3 | J25: VN | K25: Office | S25: Associate
A26: 25 | B26: 22VN00000078 | C26: anh.nguyenngoclan@mapactive.vn | D26: Nguyễn Ngọc Lan Anh | E26: Nguyen Ngoc Lan Anh | F26: Sophie | H26: Graphic Designer | I26: E3 | J26: VN | K26: Office | S26: Senior Executive
A27: 26 | B27: 22VN00000044 | C27: trinh.tranngocdoan@mapactive.vn | D27: Trần Ngọc Đoan Trinh | E27: Tran Ngoc Doan Trinh | H27: Senior Merchandise | I27: E3 | J27: VN | K27: Office | S27: Senior Manager
A28: 27 | B28: 22VN00000061 | C28: linh.lengocmy@mapactive.vn | D28: Lê Ngoc Mỹ Linh | E28: Le Ngoc My Linh | H28: Senior Merchandise | I28: E3 | J28: VN | K28: Office | L28: 44958
A29: 28 | B29: 22VN00000013 | C29: nhi.tranthiyen@mapactive.vn | D29: Trần Thị Yến Nhi | E29: Tran Thi Yen Nhi | H29: Payroll & Em. Servieces Executive | I29: E3 | J29: VN | K29: Office | S29: Senior Associate
A30: 29 | B30: 22VN00000014 | C30: ni.ksormahhko@mapactive.vn | D30: Ksormahhko NI | E30: Ni Ksormahhko | H30: Procurement Executive | I30: E3 | J30: VN | K30: Office | S30: Senior Associate
A31: 30 | B31: 22VN00000065 | C31: lan.nguyenphuong@mapactive.vn | D31: Nguyễn Phương Lan | E31: Nguyen Phuong Lan | G31: Legal | H31: Legal Manager | I31: E3 | J31: VN | K31: Office | L31: 44991 | M31: Done | N31: Done | O31: 5430 | P31: Done | Q31: Done
A32: 31 | B32: 22VN00000106 | C32: syed.umairhassan@mapactive.vn | D32: Syed Umair Hassan | E32: Syed Umair Hassan | G32: BOD (Merchandise) | H32: GM Merchandise | I32: E3 | J32: VN | K32: Office | L32: 45005 | M32: Done | Q32: Done | R32: Using the HP Laptop of Birkenstock Diamond Plaza
A33: 32 | B33: 22VN00000025 | C33: quan.luonghuu@mapactive.vn | D33: Lương Hữu Quân | E33: Luong Huu Quan | G33: IT | H33: IT Infrastructure & Operations Supervisor | I33: E3 | J33: VN | K33: Office | L33: 45012 | M33: Done | N33: Done | O33: 3520 | P33: Done | Q33: Done
A34: 33 | B34: 22VN00000015 | C34: nhan.huynhtuan@mapactive.vn | D34: Huỳnh Tuấn Nhân | E34: Huynh Tuan Nhan | G34: SCM | H34: SCM Manager | I34: E3 | J34: VN | K34: Office | L34: 45019 | M34: Done | N34: No need | O34: No need | P34: No need | R34: Re-use the laptop of ngoc.voleminh
A35: 34 | B35: 22VN00000004 | C35: mong.nguyenthithuy@mapactive.vn | D35: Nguyễn Thị Thúy Mộng | E35: Nguyen Thi Thuy Mong | G35: Merchandise | H35: Senior Brand Marketing Manager | I35: E3 | J35: VN | K35: Office | L35: 45026 | M35: Done | N35: Done | O35: 5430 | R35: Foot Locker
A36: 35 | B36: 22VN00000070 | C36: qui.nguyenthi@mapactive.vn | D36: Nguyễn Thị Quí | E36: Nguyen Thi Qui | G36: Accounting | H36: General Accountant UFO | I36: E3 | J36: VN | K36: Office | L36: 45054 | M36: Done | N36: No need | O36: No need | R36: Re-use Nguyễn Trí Độ' Laptop
A37: 36 | B37: 22VN00000072 | C37: le.daothihong@mapactive.vn | D37: Đào Thị Hồng Lê | E37: Dao Thi Hong Le | G37: Training | H37: Training Assistant Manager | I37: E3 | J37: VN | K37: Office | L37: 45069 | M37: Done | N37: done | O37: 5430
A38: 37 | B38: 22VN00000042 | C38: dien.tranduy@mapactive.vn | D38: Trần Duy Điền | E38: Tran Duy Dien | G38: COE Department | H38: Inventory Control | I38: E3 | J38: VN | K38: Office | L38: 45078 | M38: Done | N38: No need | O38: 3520
A39: 38 | B39: 22VN00000080 | C39: thu.nguyenthanhanh@mapactive.vn | D39: Nguyễn Thanh Anh Thư | E39: Nguyen Thanh Anh Thu | G39: Marketing Department | H39: Visual Merchandise Manager | I39: E3 | J39: VN | K39: Office | L39: 45083 | M39: Done | N39: Done | O39: 5430
A40: 39 | B40: 22VN00000081 | C40: Huy.daoduc@mapactive.vn | D40: Đào Đức Huy | E40: Dao Duc Huy | G40: Operations Department | H40: Area Manager (South) | I40: E3 | J40: VN | K40: Office | L40: 45110 | M40: Done | N40: Done | O40: 5430
A41: 40 | B41: 22VN00000023 | C41: du.nguyenbao@mapactive.vn | D41: Nguyễn Bảo Du | E41: Nguyen Bao Du | G41: HR Department | H41: HR Internship | I41: None | J41: VN | K41: Office | L41: 45139 | M41: No need | N41: Done | O41: Mini PC
A42: 41 | B42: 22VN00000079 | C42: duyen.lethanh@mapactive.vn | D42: Lê Thanh Duyên | E42: Le Thanh Duyen | G42: Marketing Department | H42: Graphic Designer (Foot Locker) | I42: E3 | J42: VN | K42: Office | L42: 45146 | M42: Done | N42: No need | R42: Re-use Vũ Xuân Sơn
A43: 42 | B43: 22VN00000104 | C43: ngoc.nguyenduyen@mapactive.vn | D43: Nguyễn Duyên Ngọc | E43: Nguyen Duyen Ngoc | G43: Business Development | H43: Business Development Manager | I43: E3 | J43: VN | K43: Office | L43: 45174 | M43: Done | N43: No need | O43: 5430 | P43: Done | Q43: Done | R43: Thay anh Hiếu BD (hieu.trantrung)last day ngày 31/08 dùng lại laptop | S43: Business Development Manager
A44: 43 | B44: 22VN00000028 | C44: van.nghiemthihong@mapactive.vn | D44: Nghiêm Thị Hồng Vân | E44: Nghiem Thi Hong Van | G44: Brand Department | H44: Senior Merchandise | I44: E3 | J44: VN | K44: Office | L44: 45214
A45: 44 | B45: 22VN00000052 | C45: xuan.vothihoanganh@mapactive.vn | D45: Võ Thị Hoàng Ánh Xuân | E45: Vo Thi Hoang Anh Xuan | G45: Operations | H45: Operations Executive | I45: E3 | J45: VN | K45: Office | L45: 45218 | M45: None | N45: No need | O45: 7490 | R45: Dùng lại máy ĐẶNG QUỐC TRÍ (OP)
A46: 45 | B46: 22VN00000039 | C46: tram.lengocbich@mapactive.vn | D46: Lê Ngọc BÍch Trâm | E46: Le Ngoc Bich Tram | G46: Marketing Department (Foot Locker) | H46: Marketing Supervisor (Foot Locker) | I46: E3 | J46: VN | K46: Office | L46: 45219 | M46: Done | N46: No need | O46: x280 | Q46: Done | R46: Replace Phạm Thị Mỹ Dung
A47: 46 | B47: 22VN00000051 | C47: mai.nguyenthihuynh@mapactive.vn | D47: Nguyễn Thị Huỳnh Mai | E47: Nguyen Thi Huynh Mai | F47: Maya | H47: Finance, Tax & Accounting Manager | I47: E3 | J47: VN | K47: Office | Q47: Done | R47: laptop cũ của Huỳnh Ngọc Sơn (team Project)
A48: 47 | B48: 22VN00000050 | C48: tuan.duongquangminh@mapactive.vn | D48: Dương Quang Minh Tuấn | E48: Duong Quang Minh Tuan | G48: Retail Operations Department | H48: Area Manager (South) | I48: E3 | J48: VN | K48: Office | L48: 45229 | N48: No need
A49: 48 | B49: 22VN00000053 | C49: dat.volamminh@mapactive.vn | D49: Võ Lâm Minh Đạt | E49: Vo Lam Minh Dat | G49: Retail Operations Department | H49: Area Manager (South) | I49: E3 | J49: VN | K49: Office | L49: 45243 | M49: HR requested | N49: no need | O49: 5420 | R49: (Re-use Dang's Laptop)
A50: 49 | B50: 22VN00000067 | C50: minh.lengocbao@mapactive.vn | D50: Lê Ngọc Bảo Minh | E50: Le Ngoc Bao Minh | G50: Internal Audit & Business Process Assistant Manager | H50: Risk Management & Business Process | I50: E3 | J50: VN | K50: Office | L50: 45245 | M50: HR requested | N50: no need | O50: 5430
A51: 50 | B51: 22VN00000060 | C51: anh.nguyensi@mapactive.vn | D51: Nguyễn Sĩ Anh | E51: Nguyen Si Anh | G51: Operation | H51: Acting Area Manager (North Side) | I51: E3 | J51: VN | K51: Office | L51: 45273 | M51: HR requested | N51: no need | O51: 5430 | R51: Re-use Phùng Như Quỳnh's Laptop
A52: 51 | B52: 22VN00000077 | C52: chi.tranvukim@mapactive.vn | D52: Trần Vũ Kim Chi | E52: Tran Vu Kim Chi | F52: Christine | G52: Brand | H52: Brand Division Manager (Foot Locker) | I52: E3 | J52: VN | K52: Office | L52: 45293 | M52: Done | O52: 5430 | R52: Will re-used Vicky's laptop
A53: 52 | B53: 22VN00000063 | C53: trang.taquynh@mapactive.vn | D53: Tạ Quỳnh Trang | E53: Ta Quynh Trang | G53: COE Department | H53: COE Officer | I53: E3 | J53: VN | K53: Office | L53: 45376 | M53: Done | R53: Re-use laptop Le Minh Khang
A54: 53 | B54: 22VN00000032 | C54: uyen.vuxuan@mapactive.vn | D54: Vũ Xuân Uyên | E54: Vu Xuan Uyen | G54: Marketing | H54: Marketing officer | I54: F3 | J54: VN | K54: Office | L54: 45384 | M54: Done
A55: 54 | C55: minh.vanduc@mapactive.vn | D55: Văn Đức Minh | E55: Van Duc Minh | F55: Quavo | G55: IT | H55: IT | I55: F3 | J55: VN | K55: Office | L55: 45448 | M55: Done
A56: 55 | B56: 22VN00000052 | C56: nhung.nguyenthihong01@mapactive.vn | D56: Nguyễn Thị Hồng Nhung | E56: Nguyen Thi Hong Nhung | G56: Operation | H56: Area Manager (North) | I56: E3 | J56: VN | K56: Office | L56: 45467 | M56: Done
A57: 56 | B57: 22VN00000006 | C57: chau.lehongbao@mapactive.vn | D57: Lê Hồng Bảo Châu | E57: Le Hong Bao Chau | G57: Marketing | H57: Marketing Admin | I57: E3 | J57: VN | K57: Office | L57: 45482 | M57: Done
A58: 57 | B58: 22VN00000011 | C58: Ngoc.nguyenbao@mapactive.vn | D58: Nguyễn Bảo Ngọc | E58: Nguyen Bao Ngoc | F58: Kelly | G58: Operation | H58: Division Operation Manager | I58: E3 | J58: VN | K58: Office | L58: 45509 | M58: Done
A59: 58 | B59: 22VN00000043 | C59: thu.nguyenthiminh@mapactive.vn | D59: Nguyễn Thị Minh Thư | E59: Nguyen Thi Minh Thu | G59: Brand | H59: Planning | I59: E3 | J59: VN | K59: Office | L59: 45558 | M59: Done
A60: 59 | B60: 22VN00000059 | C60: binh.nguyenmy@mapactive.vn | D60: Nguyễn Mỹ Bình | E60: Nguyen My Binh | G60: E-COMMERCE | H60: Digital Commercial Manager | I60: E3 | J60: VN | K60: Office | L60: 45796 | M60: Done | R60: Re-use laptop
A61: 61 | B61: 22VN00000010 | C61: ngan.vongocthanh@mapactive.vn | D61: Vo Ngoc Thanh Ngan | E61: Vo Ngoc Thanh Ngan | G61: Brand | H61: Intern | I61: E3 | J61: VN | K61: Office | L61: 45796 | M61: Done
A62: 62 | B62: 22VN00000094 | C62: tran.huynhkimngoc@mapactive.vn | D62: Huynh Kim Ngoc Tran | E62: Huynh Kim Ngoc Tran | G62: Accounting | H62: Intern | I62: E3 | J62: VN | K62: Office | L62: 45796 | M62: Done
A63: 63 | B63: 22VN00000105 | C63: uyen.nguyenhaphuong@mapactive.vn | D63: Nguyễn Hà Phượng Uyên | E63: Nguyen Ha Phuong Uyen | F63: Dory | G63: BOD (Finance) | H63: General Manager & Finance Controller | I63: E3 | J63: VN | K63: Office | S63: Senior General Manager
A64: 64 | B64: 22VN00000041 | C64: nhung.nguyenthituyet@mapactive.vn | D64: Nguyễn Thị Tyết Nhung | E64: Nguyen Thi Tuyet Nhung | G64: Brand | H64: Senior Merchandise | I64: E3 | J64: VN | K64: Office | L64: 45880 | M64: Done
A65: 65 | B65: 22VN00000034 | C65: giang.trana@mapactive.vn | D65: Trần A Giang | E65: Tran A giang | G65: Intern | H65: Intern | I65: F3 | J65: VN | K65: Office | L65: 45880
A66: 66 | B66: 22VN00000074 | C66: hai.nguyenthanh@mapactive.vn | D66: Nguyễn Thanh Hải | E66: Nguyen Thanh Hai | G66: Intern | H66: Intern | I66: F3 | J66: VN | K66: Office | L66: 45880
A67: 67 | B67: 22VN00000002 | C67: Doan.An@mapactive.vn | D67: Đoàn Thiên Hồ An | E67: Doan Thien Ho An | G67: E-COMMERCE | H67: Digital Marketing Manager | I67: E3 | J67: VN | K67: Office | L67: 45964 | M67: Done
A68: 68
A69: 69
A70: 70
A71: 71
A77: 1 | C77: thu.pham@mapactive.vn | D77: Phạm Nguyễn Minh Thư | E77: Pham Nguyen Minh Thu | G77: DSV | H77: Logs Coordinator DSV VN | J77: VN | K77: Warehouse
A78: 2 | C78: quan.vu@mapactive.vn | D78: Vũ Thái Quân | E78: Vu Thai Quan | G78: DSV | H78: OPS Manager DSV VN | I78: E3 | J78: VN | K78: Warehouse
A79: 3 | C79: ngoc.ngo@mapactive.vn | D79: Ngô Lê Bảo Ngọc | E79: Ngo Leo Bao Ngoc | G79: DSV | H79: Logs Coordinator DSV VN | J79: VN | K79: Warehouse
A80: 4 | C80: nguyen.thieu@mapactive.vn | D80: Nguyễn Gia Thiều | E80: Thieu Gia Nguyen | G80: DSV | H80: Logs Coordinator DSV VN | J80: VN | K80: Warehouse
A81: 5 | C81: mma.it@mapactive.vn | D81: MMA IT Vietnam | E81: MMA IT Vietnam | G81: IT | I81: E1 | J81: VN | K81: Shared | R81: IT shared email account for licensing (Owner: IT)
A82: 6 | C82: footlocker.vietnam@mapactive.vn | D82: Foot Locker Vietnam | E82: Foot Locker Vietnam | G82: Brand | I82: E1 | J82: VN | K82: Shared | R82: Foot Locker email for register with Ecom platforms (Owner: Brand - FL)
A83: 7 | C83: HR.Recruitment@mapactive.vn | D83: HR Recruitment | E83: HR Recruitment | G83: HR | I83: E1 | J83: VN | K83: Shared | R83: HR shared email account for recruitment, receive CV from candidates (Owner: HR)
A84: 8 | C84: dung.nguyenthiphuong@mapactive.vn | D84: Nguyễn Thị Phương Dung | E84: Nguyen Thị Phuong Dung | G84: Marketing Department | H84: Marketing Supervisor | I84: E3 | J84: VN | K84: Office | L84: 45240 | M84: HR requested | N84: no need | O84: 3520
A85: 9 | C85: mma.hotline@mapactive.vn | D85: MMA HOTLINE | E85: MMA HOTLINE | G85: HR | I85: E1 | J85: VN | K85: Shared
A86: 10 | C86: mac.hotline@mapactive.kh | D86: MAC HOTLINE | E86: MAC HOTLINE | G86: HR | I86: E1 | J86: KH | K86: Shared
A87: 11 | C87: mma.hotline@mapactive.vn | D87: Lưu Giang Cẩm Vân | E87: Luu Giang Cam Van | F87: Vicky | H87: HR & Admin Manager | I87: F3 | J87: VN | K87: Office | L87: 45250
A88: 12 | C88: mac.hotline@mapactive.kh | E88: TO HO | H88: HR & Admin Manager | I88: F3 | J88: KH | K88: Office | L88: 45250

Sheet Office_Resigned
A1: Disable Email | B1: No. | C1: Assigned Asset | D1: Email Address | E1: Full Name | F1: Display Name | G1: English Name | H1: Department | I1: JOB TITLE | J1: O365 license | K1: Country | L1: Type | M1: Onboarding Date (dd/mm/yy) | N1: Request email | O1: Purchasing Request | P1: Laptop model | Q1: Laptop delivery | R1: Handover to user | S1: Notes | T1: MAP Level
A3: Request ITSD, IT Server Operation on 23 Feb 2023 (Ticket : WO0000000107284) | B3: 1 | D3: alun.hughes@mapactive.vn | F3: Alun Hughes | J3: Exchange Online Kiosk
A4: Need to check with anh Nhân Log | B4: =B3+1 -> 2 | D4: loan.lethikim@mapactive.vn | I4: Shipping Executive | J4: E3 | M4: 15/02/2023 | N4: Done | P4: 3520 | Q4: Done | R4: Done | S4: đã nghỉ việc
A5: Done | B5: =B4+1 -> 3 | D5: ngoc.voleminh@mapactive.vn | I5: Logistics Manager | J5: E3 | S5: đã nghỉ việc | T5: Manager
A6: Done | B6: =B5+1 -> 4 | D6: trung.lehominh@mapactive.vn | E6: Lê Hồ Minh Trung | F6: Le Ho Minh Trung | H6: Digital | I6: Digital Commercial Senior Manager | J6: E3 | K6: VN | M6: 03/04/2023 | N6: Done | O6: Done | P6: 5430 | S6: đã nghỉ việc
A7: Done | B7: =B6+1 -> 5 | D7: tram.nguyhuynhmai@mapactive.vn | E7: Ngụy Huỳnh Mai Trâm | F7: Nguy Huynh Mai Tram | H7: Logistic | I7: Logistic Admin | J7: E3 | K7: VN | M7: 14/04/2023 | S7: đã nghỉ việc | T7: Associate
A8: Done | B8: =B7+1 -> 6 | D8: nhung.nguyenhong@mapactive.vn | E8: Nguyễn Hồng Nhung | F8: Nguyen Hong Nhung | H8: Training | I8: Training Assistant Manager | J8: E3 | K8: VN | M8: 14/04/2023 | S8: đã nghỉ việc | T8: Associate Manager
A9: Done | B9: =B8+1 -> 7 | D9: ha.dangthivan@mapactive.vn | E9: Đặng Thị Vân Hà | F9: Dang Thi Van Ha | H9: Merchandise | I9: Merchandise | K9: VN | M9: 14/04/2023 | S9: đã nghỉ việc
A10: Done | B10: =B9+1 -> 8 | D10: hau.lenguyentrung@mapactive.vn | E10: Lê Nguyễn Trung Hậu | F10: Le Nguyen Trung Hau | H10: Merchandise | I10: Visual Merchandise Supervisor | K10: VN | M10: 17/04/2023 | N10: Done | O10: Done | P10: 5430 (swap for Henry) | S10: đã nghỉ việc
A11: Done | B11: =B10+1 -> 9 | D11: do.nguyentri@mapactive.vn | E11: Nguyễn Trí Độ | F11: Nguyen Tri Do | H11: Accounting | I11: General Accounting | J11: E3 | K11: VN | M11: 03/04/2023 | N11: Done | O11: Done | P11: 5430 | S11: đã nghỉ việc
A12: Done | B12: =B11+1 -> 10 | D12: nghia.letrong@mapactive.vn | E12: Lê Trọng Nghĩa | F12: Le Trong Nghia | H12: Training | I12: Training Assistant Manager | K12: VN | M12: 24/04/2023 | N12: Done | O12: Done | P12: Re use Laptop Chị Nhung | Q12: Re use Laptop Chị Nhung | S12: đã nghỉ việc
A13: Done | B13: =B12+1 -> 11 | D13: duong.nguyenthihai@mapactive.vn | I13: Internal Audit & Business Process Assistant Manager | J13: E3 | K13: VN | M13: 01/03/2023 | N13: Done | O13: Done | P13: 5430 | Q13: Done | R13: Done | S13: đã nghỉ việc
A14: Done | B14: =B13+1 -> 12 | D14: thuy.dangtranthu@mapactive.vn | I14: Marketing Executive | J14: E3 | K14: VN | M14: 14/07/2023 | N14: Done | O14: Done | P14: 3520 | S14: Disable email after 09/2023 | T14: Executive
A15: Done | B15: =B14+1 -> 13 | D15: son.vuxuan@mapactive.vn | E15: Vũ Xuân Sơn | F15: Vu Xuan Son | H15: Marketing Department | I15: Graphic Designer (Foot Locker) | K15: vn | M15: 15/06/2023 | N15: Done | O15: Done | S15: đã nghỉ việc
A16: Need to keep until end of Oct-2023 | B16: =B15+1 -> 14 | D16: giang.nguyenthiquynh@map.co.id | I16: Merchandiser | J16: E3 | K16: VN | S16: đã nghỉ việc | T16: Senior Executive
A17: Done | B17: =B16+1 -> 15 | D17: hieu.trantrung@mapactive.vn | I17: Business Development Manager | J17: E3 | K17: VN | S17: đã nghỉ việc | T17: Manager
A18: Need to keep until Ms Uyên Confirm | B18: =B17+1 -> 16 | D18: tri.dangquoc@mapactive.vn | I18: Retail Operations Manager | J18: E3 | K18: VN | S18: đã nghỉ việc | T18: Manager
A19: Can revoke license | B19: =B18+1 -> 17 | D19: hoang.phanbao@mapactive.vn | E19: Phan Bảo Hoàng | F19: Phan Bao Hoang | I19: Area Manager (South) | J19: E3 | K19: VN | S19: đã nghỉ việc | T19: Associate Manager
A20: Done | B20: =B19+1 -> 18 | D20: quynh.tranthilam@mapactive.vn | E20: Tran Thi Lâm Quỳnh | F20: Tran Thi lam Quynh | I20: Senior Merchandise | J20: E3 | K20: VN | S20: đã nghỉ việc | T20: Associate Manager
A21: Done | B21: =B20+1 -> 19 | D21: huong.tranquocthien@mapactive.vn | F21: Tran Quoc Thien Huong | I21: Senior Merchandise Planning Manager | J21: E3 | K21: VN | T21: Senior Manager
A22: Need to keep until Kelvin confirm (Oct-2023) | B22: =B21+1 -> 20 | D22: tien.phanthithuy@mapactive.vn | E22: Phan Thị Thủy Tiên | F22: Phan Thi Thuy Tiên | H22: Marketing | I22: Marketing officer | J22: E3 | K22: VN | M22: 8/5/2023 | N22: Done | O22: No need | P22: No need | S22: re-use Le Nguyen Trung Hau's Laptop
A23: done | B23: =B22+1 -> 21 | D23: vothea.iem@map.co.id | E23: Iem Vothea | F23: Iem Vothea | H23: Accounting | I23: Assistant Accountant Manager | J23: E3 | K23: KH | N23: Done | Q23: Done
A24: done | B24: =B23+1 -> 22 | D24: khoa.trandanganh@mapactive.vn | F24: Tran Dang Anh Khoa | I24: COE Officer | J24: E3 | K24: VN | T24: Associate
B25: 1 | D25: dung.phamthimy@mapactive.vn | E25: Phạm Thị Mỹ Dung | F25: Pham Thi My Dung | H25: Marketing Department | I25: Marketing Supervisor | J25: E3 | K25: VN | L25: `` | M25: 23/06/2023 | N25: Done | O25: Done | P25: 3520
A26: Done | B26: 2 | D26: ngan.huynhthibich@mpactive.vn | E26: Huỳnh Thị Bích Ngân | F26: Huynh Thi Bich Ngan | H26: Marketing Department | I26: Marketing Executive | J26: E3 | K26: VN | L26: Office | M26: 45270 | N26: Done | O26: No need | P26: x280 | R26: Done | S26: đã nghỉ việc 13/10/2023
A27: Waiting when HR Complete proccess resign | B27: 3 | C27: 22VN00000085 | D27: hieu.nguyenvutrung@mapactive.vn | E27: Nguyễn Vũ Trung Hiếu | F27: Nguyen Vu Trung Hieu | H27: Marketing Department | I27: Marketing Supervisor | J27: E3 | K27: VN | L27: Office | M27: 45140 | N27: Done | O27: Done | P27: 3520 | Q27: Done | R27: Done
A28: Done | B28: 4 | C28: 22VN00000047 | D28: dang.hohai@mapactive.vn | E28: Hồ Hải Đăng | F28: Ho Hai Dang | I28: Area Manager (South) | J28: E3 | K28: VN | L28: Office
A29: Done | B29: 5 | C29: 22VN00000075 | D29: quynh.phungnhu@mapactive.vn | E29: Phùng Như Quỳnh | F29: Phung Nhu Quynh | I29: Area Manager (North) | J29: E3 | K29: VN | L29: Office
A30: Need to keep until we have replacement | B30: 6 | C30: 22VN00000038 | D30: Trương Hồng Hương | E30: Truong Hong Huong | F30: Jolie | H30: Brand Manager (Birkenstock) | I30: E3 | J30: VN | K30: Office | S30: Senior Manager
A31: Done | B31: 7 | C31: 22VN00000086 | D31: quynh.nguyennhu@mapactive.vn | E31: Nguyễn Như Quỳnh | F31: Nguyen Nhu Quynh | H31: Brand Department | I31: Brand Manager (Bata) | J31: E3 | K31: VN | L31: Office | M31: 45152 | N31: Done | O31: Done | P31: 5430 | S31: BM for Bata, New Era
A32: Done | B32: 22 | C32: 22VN00000029 | D32: Tram.phamthibao@mapactive.vn | E32: Phạm Thị Bảo Trâm | F32: Pham Thi Bao Tram | I32: Marketing officer | J32: E3 | K32: VN | L32: Office | T32: Associate
B33: 11 | C33: 22VN00000026 | D33: dat.tranquoc@mapactive.vn | E33: Trần Quốc Đạt | F33: Tran Quoc Dat | I33: IT Officer | J33: E3 | K33: VN | L33: Office | T33: Senior Associate
A34: Done | C34: 22VN00000049 | D34: phong.phanhoai@mapactive.vn | E34: Phan Hoài Phong | F34: Phan Hoai Phong | H34: Marketing Department | I34: Visual Merchandise Executive | J34: E3 | K34: VN | L34: Office | M34: 45078 | N34: Done | O34: No need | P34: 3520
A35: Done | C35: 22VN00000068 | D35: my.tranthitoan@mapactive.vn | E35: Trần Thị Toàn Mỹ | F35: Tran Thi Toan My | I35: Senior Planning Merchandise | J35: E3 | K35: VN | L35: Office | M35: 45012 | N35: Done | O35: Done | P35: 3520 | Q35: Done | R35: Done
B36: =Office_Resigned!A57+1 -> 19 | C36: 22VN00000052 | D36: tra.truongvantin@mapactive.vn | E36: Trương Văn tín Trà | F36: Truong Van Tin Tra | I36: Project Supervisor | J36: E3 | K36: VN | L36: Office | T36: Senior Executive
B37: 32 | C37: 22VN00000040 | D37: tien.trantrung@mapactive.vn | E37: Trần Trung Tiến | F37: Tran Trung Tien | H37: Merchandise | I37: Senior Merchandise | J37: E3 | K37: VN | L37: Office | M37: 45012 | N37: Done | O37: No need | P37: 3520 | Q37: No need | R37: Done | S37: Replace Diệp team Ms. Jolie will resign on 10/04. Provide temporary MiniPC to use
B38: =Office_Resigned!A64+1 -> 20 | C38: 22VN00000009 | D38: hoa.mailecam@mapactive.vn | E38: Mai Lê Cẩm Hòa | F38: Mai Le Cam Hoa | G38: Mia | I38: Retail Admin Executive | J38: E3 | K38: VN | L38: Office | T38: Senior Executive
B39: =Office_Resigned!B45+1 -> #VALUE! | C39: 22VN00000094 | D39: minh.letranthien@mapactive.vn | E39: Lê Trần Thiên Minh | F39: Le Tran Thien Minh | H39: Operations Department | I39: Retail Operations Division Manager | J39: E3 | K39: VN | L39: Office | M39: 45136 | N39: Done | O39: Done | P39: 5430
B40: =VN_Emails!A27+1 -> 27 | C40: 22VN00000039 | D40: linh.thainhat@mapactive.vn | E40: Thái Nhật Linh | F40: Thai Nhat Linh | I40: Merchandiser | J40: E3 | K40: VN | L40: Office | T40: Senior Executive
B41: =Office_Resigned!A48+1 -> 21 | C41: 22VN00000062 | D41: loan.nguyenhoang@mapactive.vn | E41: Nguyễn Hoàng Loan | F41: Nguyen Hoang Loan | I41: Project Supervisor | J41: E3 | K41: VN | L41: Office | M41: 44984 | N41: Done | O41: Done | P41: 3520 | Q41: Done | R41: Done
A42: Done | B42: =VN_Emails!#REF!+1 -> #REF! | D42: it.vn@mapactive.vn | E42: Nguyễn Phạm Duy Anh | F42: Nguyen Pham Duy Anh | H42: IT | I42: IT Officer | J42: F3 | K42: VN | L42: Office | M42: 45383 | N42: Done
B43: 22VN00000077 | C43: hien.nguyendo@mapactive.vn | D43: Nguyễn Đỗ Hiền | E43: Nguyen Do Hien | G43: Brand | H43: Merchandise Manager (Foot Locker) | I43: E3 | J43: VN | K43: Office | L43: 45075 | M43: Done | N43: done | O43: 5430
A44: Already disable email account and revoke lic | B44: 22VN00000084 | C44: huan.lenam@mapactive.vn | D44: Lê Nam Huân | E44: Le Nam Huan | G44: Training Department | H44: Training Executive | I44: E3 | J44: VN | K44: Office | L44: 45118 | M44: Done | N44: Done | O44: 3520
B45: 22VN00000083 | C45: nhung.nguyenthituyet@mapactive.vn | D45: Nguyễn Thị Tuyết Nhung | E45: Nguyen Thi Tuyet Nhung | G45: Planning Department | H45: Senior Merchandise Planning | I45: E3 | J45: VN | K45: Office | L45: 45124 | M45: Done | N45: Done | O45: 3520
A46: =Office_Resigned!A47+1 -> 44 | B46: 22VN00000064 | C46: Tuyet.tranthikim@mapactive.vn | D46: Trần Thị Kim Tuyết | E46: Tran Thi kim Tuyet | G46: Operations Department | H46: Retail Operations Division Manager (Foot Locker) | I46: E3 | J46: VN | K46: Office | L46: 45180 | M46: Done | N46: Done | O46: 5430 | P46: Done | Q46: Done
A47: =VN_Emails!A43+1 -> 43 | B47: 22VN00000090 | D47: Hoàng Thân Bảo Phúc | E47: Hoang Than Bao Phuc | G47: Marketing Department | H47: Marketing intern | I47: None | J47: VN | K47: Office | L47: 45176 | M47: None | N47: No need | O47: Mini PC
A48: =Office_Resigned!A64+1 -> 20 | C48: uyen.vuthuy@mapactive.vn | D48: Vũ Thùy Uyên | E48: Vu Thuy Uyen | H48: COE Officer | I48: E3 | J48: VN | K48: Office | L48: 44980 | M48: Done | N48: Done | O48: 3520 | P48: Done | Q48: Done
A49: =VN_Emails!A29+1 -> 29 | B49: 22VN00000010 | C49: trang.huynhthimy@mapactive.vn | D49: Huỳnh Thị Mỹ Trang | E49: Huynh Thi My Trang | H49: Retail Admin | I49: E3 | J49: VN | K49: Office | S49: Associate
A50: =VN_Emails!A34+1 -> 34 | B50: 22VN00000071 | C50: an.nguyenhuu@mapactive.vn | D50: Nguyễn Hữu An | E50: Nguyen Huu An | G50: IT | H50: IT Application & Analytic Associate Manager | I50: E3 | J50: VN | K50: Office | L50: 45026 | M50: Done | N50: Done | O50: 5430
A51: =Office_Resigned!A57+1 -> 19 | B51: 22VN00000025 | C51: hieu.phamtrung@mapactive.vn | D51: Phạm Trung Hiếu | E51: Pham Trung Hieu | H51: IT Infrastructure & Operations Manager | I51: E3 | J51: VN | K51: Office | S51: Manager
A52: =VN_Emails!A42+1 -> 42 | B52: 22VN00000087 | C52: dung.huynhkim@mapactive.vn | D52: Huỳnh Kim Dung | E52: Huynh Kim Dung | F52: Zoe | G52: Brand Department | H52: Senior Merchandise | I52: E3 | J52: VN | K52: Office | L52: 45159 | M52: Done | N52: Done | O52: 3520 | P52: Done | Q52: Done
A53: =VN_Emails!A55+1 -> 55 | B53: 22VN00000084 | C53: luong.lactuan@mapactive.vn | D53: Lạc Tuấn Lương | E53: Lac Tuan Luong | G53: Training Department | H53: Training Assistant | I53: F3 | J53: VN | K53: Office | L53: 45453 | M53: Done
A54: 19 | B54: 22VN00000066 | C54: tram.nguyenthibich@mapactive.vn | D54: Nguyễn Thị Bích Trâm | E54: Nguyen Thi Bich Tram | G54: SCM | H54: Shipping Officer | I54: E3 | J54: VN | K54: Office | L54: 44986 | M54: Done | N54: Done | O54: 3520 | P54: Done | Q54: Done | R54: Re-use the laptop of Lê Thị Kim Loan – Shipping Executive – On board 15/02/2023 but resigned about 2 days later
A55: =VN_Emails!A58+1 -> 58 | B55: 22VN00000010 | C55: vy.huynhnguyenlan@mapactive.vn | D55: Huỳnh Nguyễn Lan Vy | E55: Huynh Nguyen Lan Vy | G55: Finance | H55: Accountant | I55: E3 | J55: VN | K55: Office | L55: 45484 | M55: Done
A56: =VN_Emails!A21+1 -> 21 | B56: 22VN00000068 | C56: van.phungboi@mapactive.vn | D56: Phùng Bội Vân | E56: Phung Boi Van | H56: Sales Online | I56: E3 | J56: VN | K56: Office | L56: 45596 | S56: Associate
A57: 18 | B57: 22VN00000094 | C57: thy.nguyenhoanganh@mapactive.vn | D57: Nguyễn Hoàng Anh Thy | E57: Nguyen Hoang Anh Thy | H57: Payable Accountant | I57: E3 | J57: VN | K57: Office | L57: 45597 | S57: Associate
A58: 19 | B58: 22VN00000095 | C58: binh.nguyenthihongminh | D58: Nguyen Thi Hong Minh Binh | E58: Nguyen Thi Hong Minh Binh | G58: MKT | H58: MKT | I58: F3 | J58: VN | K58: Office | L58: 45590
A59: 1 | B59: 22VN00000001 | C59: darryl.peacock@mapactive.vn | D59: Peacock Darryl James | E59: Peacock Darryl James | F59: Darryl | G59: BOD | H59: Country Manager | I59: E3 | J59: VN | K59: Office | S59: Vice President
A60: =VN_Emails!A86+1 -> 11 | B60: 22VN00000030 | C60: my.nguyenthao@mapactive.vn | D60: Nguyễn Thảo My | E60: Nguyen Thao My | G60: Marketing | H60: Marketing Executive | I60: E3 | J60: VN | K60: Office | L60: 45257 | M60: HR requested | N60: no need | O60: x280 | R60: re-use laptop Phan Thi Thuy Tien (AMMAVNITC000030)
A61: 26 | B61: 22VN00000082 | C61: duy.lehuynh@mapactive.vn | D61: Lê Huỳnh Duy | G61: Merchandise Department | H61: Senior Merchandiser (Foot Locker) | I61: E3 | J61: VN | K61: Office | L61: 45110 | M61: Done | N61: Done | O61: 3520
B62: 22VN00000095 | C62: tam.minh@mapactive.vn | D62: Võ Minh Tâm | E62: Vo Minh Tam | G62: Graphic Design Freelance | H62: Marketing | I62: F3 | J62: VN | K62: Office | L62: 45624 | M62: Done | N62: Done | O62: x280
A63: 25 | B63: 22VN00000003 | C63: trang.khongthithuy@mapactive.vn | D63: Khổng Thị Thùy Trang | E63: Khong Thi Thuy Trang | G63: Brand Department | H63: Senior Merchandise | I63: E3 | J63: VN | K63: Office | L63: 45110 | M63: Done | N63: Done
A64: =Office_Resigned!A57+1 -> 19 | B64: 22VN00000053 | C64: nam.vonguyenhoang@mapactive.vn | D64: Võ Nguyễn Hoàng Nam | E64: Vo Nguyen Hoang Nam | H64: Wholesale Associate Manager | I64: E3 | J64: VN | K64: Office | S64: Associate Manager
A65: 3 | B65: 22VN00000027 | C65: khen.hoanghong@mapactive.vn | D65: Hoàng Hồng Khen | E65: Hoang Hong Khen | F65: Kevin | H65: Marketing Communications Manager | I65: E3 | J65: VN | K65: Office | S65: Manager
A66: 28 | B66: 22VN00000032 | C66: Hong.lethikim@mapactive.vn | D66: Lê Thị Kim Hồng | E66: Le Thi Kim Hong | G66: Legal Department | H66: Legal Officer | I66: E3 | J66: VN | K66: Office | L66: 45180 | M66: Done | N66: No need | O66: 3420 | P66: Done | Q66: Done | R66: Dùng lại máy Trần Thị Lâm Quỳnh (MD)
A67: 45 | B67: 22VN00000022 | C67: coe.vn@mapactive.vn | D67: Trần Hồ Duy Tân | E67: Tran Ho Duy Tan | G67: COE | H67: COE Collaborator | I67: F3 | J67: VN | K67: Office | M67: Done
A68: 47 | B68: 22VN00000095 | C68: tam.minh@mapactive.vn | D68: Võ Minh Tâm | E68: Vo Minh Tam | G68: Graphic Design Freelance | H68: Marketing | I68: F3 | J68: VN | K68: Office | L68: 45601 | M68: Done
A69: =A68+1 -> 48 | B69: 22VN00000076 | C69: minh.vuba@mapactive.vn | D69: Vũ Bá Minh | E69: Vu Ba Minh | G69: Digital Department | H69: Digital Commercial Manager | I69: E3 | J69: VN | K69: Office | L69: 45075 | M69: Done | N69: done | O69: 5430
A70: 5 | B70: 22VN00000058 | C70: dai.lamhoangphuoc@mapactive.vn | D70: Lâm Hoàng Phước Đại | E70: Lam Hoang Phuoc Dai | H70: Digital Marketing Manager | I70: E3 | J70: VN | K70: Office | S70: Manager
A71: 69 | B71: 22VN00000009 | C71: hien.lethithu@mapactive.vn | D71: Lê Thị Thu Hiền | E71: Le Thi Thu Hien | G71: Finance | I71: F3 | J71: VN | K71: Office | L71: 45404 | M71: Done
A72: 63 | C72: linh.hoangdieu@mapactive.vn | D72: Hoàng Diệu Linh | E72: Hoang Dieu Linh | G72: Operation | H72: Acting Area Manager (North Side) | I72: E3 | J72: VN | K72: Office | L72: 45273 | M72: Done | N72: no need | O72: Need to check | R72: Need to check
A73: 27 | B73: 22VN00000034 | C73: my.nguyenthituyet@mapactive.vn | D73: Nguyễn Thị Tuyết My | E73: Nguyen Thi Tuyet My | H73: Merchandiser | I73: E3 | J73: VN | K73: Office | S73: Senior Executive
A74: 34 | B74: 22VN00000017 | C74: bao.nguyenthanh@mapactive.vn | D74: Nguyễn Thanh Bảo | E74: Nguyen Thanh Bao | G74: Logistic | H74: Warehouse & Distribution Officer | I74: E3 | J74: VN | K74: Office | L74: 45015 | M74: Done | N74: No need | O74: No need | P74: No need | Q74: Done | R74: Replace Ngụy Huỳnh Mai Trâm will resign on 14/04/2023. Provide temporary MiniPC to use
A75: 60 | B75: 22VN00000023 | C75: thai.huynhquang@map.co.id | D75: Huynh Quang Thai | E75: Huynh Quang Thai | G75: HR | H75: Intern | I75: F3 | J75: VN | K75: Office | L75: 45810 | M75: Done
